Workbook

Sheet Assumptions
A1: NRES SDA ROTA MANAGEMENT SYSTEM — KEY ASSUMPTIONS
A2: Yellow cells are adjustable inputs — changes cascade to all tabs via formulas
A4: CONTRACT PARAMETERS
A5: Parameter | B5: Value | C5: Unit | D5: Source / Notes
A6: Per-patient funding rate | B6: 26.33 | C6: £/patient/year | D6: ICB Enhanced Service spec
A7: Total registered patients | B7: 89584 | C7: patients | D7: Feb 2026 list sizes — adjustable below
A8: Annual contract value | B8: =B6*B7 -> 2358746.7 | C8: £ | D8: Auto-calculated
A9: Contract start date | B9: 01/04/2026 | C9: date | D9: Financial year start
A10: Non-winter weeks | B10: 39 | C10: weeks | D10: Standard period
A11: Winter weeks | B11: 13 | C11: weeks | D11: Enhanced delivery Nov–Feb
A12: Total operating weeks | B12: =B10+B11 -> 52 | C12: weeks
A13: Non-winter appt rate | B13: 15.2 | C13: per 1,000/wk | D13: ICB spec minimum
A14: Winter appt rate | B14: 18.2 | C14: per 1,000/wk | D14: ICB spec minimum
A15: F2F / Remote split | B15: 0.5 | C15: % each | D15: 50% remote
A16: Overhead / buffer % | B16: 0.25 | C16: % of allocation | D16: 25% for overheads
A17: On-costs % | B17: 0.2938 | C17: % | D17: Employer NI + pension
A18: Monthly instalments | B18: 12 | C18: per year | D18: Equal 1/12th payments
A21: STAFF TYPE SESSION CONFIGURATION (BMA Standard Session = 4hrs 10mins / 250 mins)
A22: Staff Type | B22: Appts/Session (F2F) | C22: Appt Duration F2F (mins) | D22: Appts/Session (Remote) | E22: Appt Duration Remote (mins) | F22: Buy-Back Rate/Session (£)
A23: GP | B23: 12 | C23: 15 | D23: 12 | E23: 15 | F23: 11000
A24: ACP | B24: 12 | C24: 15 | D24: 12 | E24: 15
A25: ANP | B25: 12 | C25: 15 | D25: 12 | E25: 15
A26: Additional roles (Paramedic, Clinical Pharmacist, PA, FCP, MHP): configurable in system — same defaults (12 appts × 15 mins). Buy-back rates TBC.
A27: PRACTICE LIST SIZES (ADJUSTABLE — UPDATE QUARTERLY)
A28: Practice | B28: List Size | C28: Hub/Spoke | D28: Clinical System | E28: % of Total
A29: The Parks MC | B29: 22827 | C29: HUB | D29: SystmOne | E29: =B29/B36 -> 0.25481113
A30: Brackley MC | B30: 16212 | C30: HUB | D30: SystmOne | E30: =B30/B36 -> 0.18096982
A31: Springfield Surgery | B31: 12611 | C31: SPOKE | D31: EMIS | E31: =B31/B36 -> 0.14077291
A32: Towcester MC | B32: 11748 | C32: SPOKE | D32: EMIS | E32: =B32/B36 -> 0.13113949
A33: Bugbrooke Surgery | B33: 10788 | C33: SPOKE | D33: SystmOne | E33: =B33/B36 -> 0.12042329
A34: Brook Health Centre | B34: 9069 | C34: SPOKE | D34: SystmOne | E34: =B34/B36 -> 0.1012346
A35: Denton Village Surgery | B35: 6329 | C35: SPOKE | D35: SystmOne | E35: =B35/B36 -> 0.070648777
A36: TOTAL | B36: =SUM(B29:B35) -> 89584 | E36: =SUM(E29:E35) -> 1
A38: MANAGEMENT & PROGRAMME RATES (From 1st April 2026)
A39: Role | B39: Hourly Rate (£) Inc On Costs | C39: Hours/Week | D39: Weeks/Year | E39: Annual Cost | F39: Reclaim Method
A40: Senior Responsible Officer (SRO) - Dr Mark Gray | F40: Claimed from PML
A41: SNO Programme Director | F41: Claimed from PML
A42: Clinical Lead - Dr Simon Ellis | F42: Claimed from TMC
A43: Managerial Lead - Amanda Palin | B43: 30 | C43: 6 | D43: 46 | E43: =B43*C43*D43*(1+B17) -> 10712.664 | F43: Claimed from B&T PCN
A44: Managerial Lead Support - Lucy Hibberd | B44: 30 | C44: 4 | D44: 46 | E44: =B44*C44*D44 -> 5520 | F44: Claimed from BMP
A45: Digital and Estates Support - Alex Whitehead | B45: 30 | C45: 4 | D45: 46 | E45: =B45*C45*D45 -> 5520 | F45: Claimed from The Parks
A46: Digital & Estates Lead - Malcolm Railson | B46: 0 | C46: 4 | D46: 46 | E46: =B46*C46*D46*(1+B17) -> 0 | F46: Part of PCN Role
A47: SNO Admin Costs TBC | F47: Claimed from PML
A48: Member Practice PM Meeting Attendance Reimbursements | F48: £50 per hour
A49: Member Practice GP Meeting Attendance Reimbursements | F49: £100 per hour

Sheet Practice Allocations
A1: NRES PRACTICE ALLOCATIONS & WEEKLY TARGETS
A2: All values formula-driven from Assumptions tab — update list sizes there
A3: Practice | B3: List Size | C3: % of Total | D3: Annual Allocation (£) | E3: Monthly Instalment (£) | F3: Recruit Budget 75% (£) | G3: Wkly Min (Non-Winter) | H3: F2F (50%) | I3: Remote (50%) | J3: Wkly Min (Winter) | K3: F2F (50%) | L3: Remote (50%) | M3: Annual Target (Appts) | N3: Hub/Spoke
A4: =Assumptions!A29 -> The Parks MC | B4: 22827 | C4: =B4/B11 -> 0.25481113 | D4: =B4*Assumptions!B6 -> 601034.91 | E4: =D4/Assumptions!B18 -> 50086.243 | F4: =D4*(1-Assumptions!B16) -> 450776.18 | G4: =(B4/1000)*Assumptions!B13 -> 346.9704 | H4: =G4*Assumptions!B15 -> 173.4852 | I4: =G4*Assumptions!B15 -> 173.4852 | J4: =(B4/1000)*Assumptions!B14 -> 415.4514 | K4: =J4*Assumptions!B15 -> 207.7257 | L4: =J4*Assumptions!B15 -> 207.7257 | M4: =(G4*Assumptions!B10)+(J4*Assumptions!B11) -> 18932.714 | N4: =Assumptions!C29 -> HUB
A5: =Assumptions!A30 -> Brackley MC | B5: 16212 | C5: =B5/B11 -> 0.18096982 | D5: =B5*Assumptions!B6 -> 426861.96 | E5: =D5/Assumptions!B18 -> 35571.83 | F5: =D5*(1-Assumptions!B16) -> 320146.47 | G5: =(B5/1000)*Assumptions!B13 -> 246.4224 | H5: =G5*Assumptions!B15 -> 123.2112 | I5: =G5*Assumptions!B15 -> 123.2112 | J5: =(B5/1000)*Assumptions!B14 -> 295.0584 | K5: =J5*Assumptions!B15 -> 147.5292 | L5: =J5*Assumptions!B15 -> 147.5292 | M5: =(G5*Assumptions!B10)+(J5*Assumptions!B11) -> 13446.233 | N5: =Assumptions!C30 -> HUB
A6: =Assumptions!A31 -> Springfield Surgery | B6: 12611 | C6: =B6/B11 -> 0.14077291 | D6: =B6*Assumptions!B6 -> 332047.63 | E6: =D6/Assumptions!B18 -> 27670.636 | F6: =D6*(1-Assumptions!B16) -> 249035.72 | G6: =(B6/1000)*Assumptions!B13 -> 191.6872 | H6: =G6*Assumptions!B15 -> 95.8436 | I6: =G6*Assumptions!B15 -> 95.8436 | J6: =(B6/1000)*Assumptions!B14 -> 229.5202 | K6: =J6*Assumptions!B15 -> 114.7601 | L6: =J6*Assumptions!B15 -> 114.7601 | M6: =(G6*Assumptions!B10)+(J6*Assumptions!B11) -> 10459.563 | N6: =Assumptions!C31 -> SPOKE
A7: =Assumptions!A32 -> Towcester MC | B7: 11748 | C7: =B7/B11 -> 0.13113949 | D7: =B7*Assumptions!B6 -> 309324.84 | E7: =D7/Assumptions!B18 -> 25777.07 | F7: =D7*(1-Assumptions!B16) -> 231993.63 | G7: =(B7/1000)*Assumptions!B13 -> 178.5696 | H7: =G7*Assumptions!B15 -> 89.2848 | I7: =G7*Assumptions!B15 -> 89.2848 | J7: =(B7/1000)*Assumptions!B14 -> 213.8136 | K7: =J7*Assumptions!B15 -> 106.9068 | L7: =J7*Assumptions!B15 -> 106.9068 | M7: =(G7*Assumptions!B10)+(J7*Assumptions!B11) -> 9743.7912 | N7: =Assumptions!C32 -> SPOKE
A8: =Assumptions!A33 -> Bugbrooke Surgery | B8: 10788 | C8: =B8/B11 -> 0.12042329 | D8: =B8*Assumptions!B6 -> 284048.04 | E8: =D8/Assumptions!B18 -> 23670.67 | F8: =D8*(1-Assumptions!B16) -> 213036.03 | G8: =(B8/1000)*Assumptions!B13 -> 163.9776 | H8: =G8*Assumptions!B15 -> 81.9888 | I8: =G8*Assumptions!B15 -> 81.9888 | J8: =(B8/1000)*Assumptions!B14 -> 196.3416 | K8: =J8*Assumptions!B15 -> 98.1708 | L8: =J8*Assumptions!B15 -> 98.1708 | M8: =(G8*Assumptions!B10)+(J8*Assumptions!B11) -> 8947.5672 | N8: =Assumptions!C33 -> SPOKE
A9: =Assumptions!A34 -> Brook Health Centre | B9: 9069 | C9: =B9/B11 -> 0.1012346 | D9: =B9*Assumptions!B6 -> 238786.77 | E9: =D9/Assumptions!B18 -> 19898.897 | F9: =D9*(1-Assumptions!B16) -> 179090.08 | G9: =(B9/1000)*Assumptions!B13 -> 137.8488 | H9: =G9*Assumptions!B15 -> 68.9244 | I9: =G9*Assumptions!B15 -> 68.9244 | J9: =(B9/1000)*Assumptions!B14 -> 165.0558 | K9: =J9*Assumptions!B15 -> 82.5279 | L9: =J9*Assumptions!B15 -> 82.5279 | M9: =(G9*Assumptions!B10)+(J9*Assumptions!B11) -> 7521.8286 | N9: =Assumptions!C34 -> SPOKE
A10: =Assumptions!A35 -> Denton Village Surgery | B10: 6329 | C10: =B10/B11 -> 0.070648777 | D10: =B10*Assumptions!B6 -> 166642.57 | E10: =D10/Assumptions!B18 -> 13886.881 | F10: =D10*(1-Assumptions!B16) -> 124981.93 | G10: =(B10/1000)*Assumptions!B13 -> 96.2008 | H10: =G10*Assumptions!B15 -> 48.1004 | I10: =G10*Assumptions!B15 -> 48.1004 | J10: =(B10/1000)*Assumptions!B14 -> 115.1878 | K10: =J10*Assumptions!B15 -> 57.5939 | L10: =J10*Assumptions!B15 -> 57.5939 | M10: =(G10*Assumptions!B10)+(J10*Assumptions!B11) -> 5249.2726 | N10: =Assumptions!C35 -> SPOKE
A11: NEIGHBOURHOOD TOTAL | B11: =SUM(B4:B10) -> 89584 | C11: =SUM(C4:C10) -> 1 | D11: =SUM(D4:D10) -> 2358746.7 | E11: =SUM(E4:E10) -> 196562.23 | F11: =SUM(F4:F10) -> 1769060 | G11: =SUM(G4:G10) -> 1361.6768 | H11: =SUM(H4:H10) -> 680.8384 | I11: =SUM(I4:I10) -> 680.8384 | ... M11: =SUM(M4:M10) -> 74300.97
A25: From Michael Chapman 19.02.26
A26: K Code | B26: Practice Name | C26: Actual List (April 25) | D26: Actual List (Jan 26) | E26: Variance
A27: K83018 | B27: Springfield Surgery | C27: 12649 | D27: 12611 | E27: -38
A28: K83022 | B28: Paulerspury Surgery | E28: 0
A29: K83022 | B29: Towcester Medical Centre | C29: 11439 | D29: 11748 | E29: 309
A30: K83049 | B30: Brackley Medical Centre | C30: 16128 | D30: 16212 | E30: 84
A31: K83052 | B31: Grange Park | E31: 0
A32: K83052 | B32: Hanslope Surgery | E32: 0
A33: K83052 | B33: Roade Medical Centre | E33: 0
A34: K83052 | B34: The Parks Medical Practice | C34: 22689 | D34: 22827 | E34: 138
A35: K83068 | B35: Denton Village Surgery | C35: 6277 | D35: 6329 | E35: 52
A36: K83070 | B36: Bugbrooke Surgery | C36: 10773 | D36: 10788 | E36: 15
A37: K83620 | B37: Silverstone Surgery | E37: 0
A38: K83620 | B38: The Brook Health Centre (Towcester) | C38: 8983 | D38: 9069 | E38: 86
A39: Neighbourhood list size | C39: 88938 | D39: 89584 | E39: 646
A41: Additional appointments required P/W | C41: 1349 | D41: 1359 | E41: 10
A42: Additional appointments required P/W serge | C42: 1619 | D42: 1631 | E42: 12
A44: New Models of Care Total Amount | C44: 2341737.5 | D44: 2358746.7 | E44: 17009.18

Sheet Room Capacity
A1: AVAILABLE CLINICAL ROOMS BY DAY & SESSION (APPOINTMENTS)
A2: Yellow cells are editable — update as estate changes. 1 session = 12 appointments (default)
A3: Session | B3: The Parks (4 sites) | C3: Springfield | D3: Brackley | E3: Brook | F3: Bugbrooke | G3: Denton | H3: Towcester | I3: Total
A4: Monday AM | B4: 12 | C4: 12 | D4: 24 | E4: 12 | F4: 12 | G4: 0 | H4: 12 | I4: =SUM(B4:H4) -> 84
A5: Monday PM | B5: 36 | C5: 12 | D5: 24 | E5: 12 | F5: 12 | G5: 0 | H5: 36 | I5: =SUM(B5:H5) -> 132
A6: Tuesday AM | B6: 60 | C6: 12 | D6: 24 | E6: 12 | F6: 12 | G6: 12 | H6: 0 | I6: =SUM(B6:H6) -> 132
A7: Tuesday PM | B7: 72 | C7: 12 | D7: 24 | E7: 12 | F7: 12 | G7: 12 | H7: 24 | I7: =SUM(B7:H7) -> 168
A8: Wednesday AM | B8: 0 | C8: 12 | D8: 24 | E8: 12 | F8: 12 | G8: 0 | H8: 12 | I8: =SUM(B8:H8) -> 72
A9: Wednesday PM | B9: 0 | C9: 12 | D9: 24 | E9: 12 | F9: 12 | G9: 0 | H9: 48 | I9: =SUM(B9:H9) -> 108
A10: Thursday AM | B10: 48 | C10: 12 | D10: 24 | E10: 12 | F10: 12 | G10: 0 | H10: 0 | I10: =SUM(B10:H10) -> 108
A11: Thursday PM | B11: 48 | C11: 12 | D11: 24 | E11: 12 | F11: 12 | G11: 12 | H11: 0 | I11: =SUM(B11:H11) -> 120
A12: Friday AM | B12: 36 | C12: 12 | D12: 24 | E12: 12 | F12: 12 | G12: 0 | H12: 24 | I12: =SUM(B12:H12) -> 120
A13: Friday PM | B13: 36 | C13: 12 | D13: 24 | E13: 12 | F13: 12 | G13: 0 | H13: 48 | I13: =SUM(B13:H13) -> 144
A14: WEEKLY TOTAL | B14: =SUM(B4:B13) -> 348 | C14: =SUM(C4:C13) -> 120 | D14: =SUM(D4:D13) -> 240 | E14: =SUM(E4:E13) -> 120 | F14: =SUM(F4:F13) -> 120 | G14: =SUM(G4:G13) -> 36 | H14: =SUM(H4:H13) -> 204 | I14: =SUM(I4:I13) -> 1188
A16: PRACTICE ESTATE SUMMARY
A17: Practice | B17: Weekly On-Site Appts | C17: Hub/Spoke | D17: Clinical System | E17: Non-Winter Remote Need | F17: Winter Remote Need
A18: The Parks MC | B18: =B14 -> 348 | C18: HUB | D18: SystmOne
A19: Springfield | B19: =C14 -> 120 | C19: HUB | D19: SystmOne
A20: Brackley MC | B20: =D14 -> 240 | C20: SPOKE | D20: EMIS
A21: Brook Health | B21: =E14 -> 120 | C21: SPOKE | D21: EMIS
A22: Bugbrooke | B22: =F14 -> 120 | C22: SPOKE | D22: SystmOne
A23: Denton Village | B23: =G14 -> 36 | C23: SPOKE | D23: SystmOne
A24: Towcester MC | B24: =H14 -> 204 | C24: SPOKE | D24: SystmOne
A26: CAPACITY GAP ANALYSIS
A27: Total on-site capacity/week | B27: =I14 -> 1188
A28: Non-Winter target/week | B28: ='Practice Allocations'!G11 -> 1361.6768
A29: Winter target/week | B29: ='Practice Allocations'!J11 -> 1630.4288
A30: Remote needed (Non-Winter) | B30: =MAX(0,B28-B27) -> 173.6768
A31: Remote needed (Winter) | B31: =MAX(0,B29-B27) -> 442.4288

Sheet Weekly Rota
A1: WEEKLY ROTA — SDA SESSION TRACKER
A2: Week Number: | B2: 1 | C2: Period: | D2: Non-Winter | E2: Practice Filter: | F2: ALL
A4: Day | B4: Session | C4: Practice | D4: Staff Name | E4: Staff Type | F4: Provision Type | G4: Appts | H4: Delivery Mode | I4: Location/Site | J4: Remote? | K4: Notes | L4: Cost Est (£)
A107: WEEKLY ROTA SUMMARY
A108: Metric | B108: Value
A109: Total sessions scheduled | B109: =COUNTA(D5:D104) -> 0
A110: Total appointments | B110: =SUM(G5:G104) -> 0
A111: New SDA appointments | B111: =SUMIF(F5:F104,"New SDA",G5:G104) -> 0
A112: Buy-Back appointments | B112: =SUMIF(F5:F104,"Buy-Back",G5:G104) -> 0
A113: Remote appointments | B113: =SUMIF(J5:J104,"Yes",G5:G104) -> 0
A114: F2F appointments | B114: =SUMIF(J5:J104,"No",G5:G104) -> 0
A115: Remote % | B115: =IF(B110>0,B113/B110,0) -> 0
A116: Buy-Back % | B116: =IF(B110>0,B112/B110,0) -> 0

Sheet Buy-Back Tracker
A1: BUY-BACK SCHEME TRACKER — OPEN BOOK ACCOUNTING
A2: All buy-back applications must be approved by Dr Mark Gray (SNO). Standard GP buy-back rate: £11,000/session. Open book — visible to all practices.
A4: BUY-BACK APPLICATIONS
A5: Ref | B5: Practice | C5: Staff Name | D5: Staff Role | E5: Sessions/Wk | F5: Buy-Back Rate (£/session) | G5: Annual Cost (£) | H5: On-Costs % | I5: Total inc On-Costs (£) | J5: Same-Day % | K5: Buy-Back Claim Value (£) | L5: SDA Appts/Wk | M5: Status | N5: Approved By | O5: Approval Date | P5: Reinvestment Plan
A6: BB-001 | B6: Denton Village Surgery | C6: TBC — New GP Recruit | D6: GP | E6: 8 | F6: 11000 | G6: =IF(E6="","",E6*F6) -> 88000 | H6: =IF(E6="","",Assumptions!B17) -> 0.2938 | I6: =IF(G6="","",G6*(1+H6)) -> 113854.4 | J6: 1 | K6: =IF(I6="","",I6*J6) -> 113854.4 | L6: 96 | M6: Draft | P6: Recruit 8-session GP at £11K-£12K DOE for proactive care
A7: BB-002 | B7: Towcester MC | C7: N/A — SEE NOTES | D7: GP + ACP | G7: =IF(E7="","",E7*F7) | H7: =IF(E7="","",Assumptions!B17) | I7: =IF(G7="","",G7*(1+H7)) | K7: =IF(I7="","",I7*J7) | M7: N/A | P7: ⚠️ NOT A BUY-BACK — Towcester currently below target (62%). New staff = New SDA to meet minimum, not buy-back. Recruitment proceeds but classified as New SDA provision.
A8: BB-003 | G8: =IF(E8="","",E8*F8) | H8: =IF(E8="","",Assumptions!B17) | I8: =IF(G8="","",G8*(1+H8)) | K8: =IF(I8="","",I8*J8)
A9: BB-004 | G9: =IF(E9="","",E9*F9) | H9: =IF(E9="","",Assumptions!B17) | I9: =IF(G9="","",G9*(1+H9)) | K9: =IF(I9="","",I9*J9)
A10: BB-005 | G10: =IF(E10="","",E10*F10) | H10: =IF(E10="","",Assumptions!B17) | I10: =IF(G10="","",G10*(1+H10)) | K10: =IF(I10="","",I10*J10)
A11: BB-006 | G11: =IF(E11="","",E11*F11) | H11: =IF(E11="","",Assumptions!B17) | I11: =IF(G11="","",G11*(1+H11)) | K11: =IF(I11="","",I11*J11)
A12: BB-007 | G12: =IF(E12="","",E12*F12) | H12: =IF(E12="","",Assumptions!B17) | I12: =IF(G12="","",G12*(1+H12)) | K12: =IF(I12="","",I12*J12)
A13: BB-008 | G13: =IF(E13="","",E13*F13) | H13: =IF(E13="","",Assumptions!B17) | I13: =IF(G13="","",G13*(1+H13)) | K13: =IF(I13="","",I13*J13)
A14: BB-009 | G14: =IF(E14="","",E14*F14) | H14: =IF(E14="","",Assumptions!B17) | I14: =IF(G14="","",G14*(1+H14)) | K14: =IF(I14="","",I14*J14)
A15: BB-010 | G15: =IF(E15="","",E15*F15) | H15: =IF(E15="","",Assumptions!B17) | I15: =IF(G15="","",G15*(1+H15)) | K15: =IF(I15="","",I15*J15)
A16: BB-011 | G16: =IF(E16="","",E16*F16) | H16: =IF(E16="","",Assumptions!B17) | I16: =IF(G16="","",G16*(1+H16)) | K16: =IF(I16="","",I16*J16)
A17: BB-012 | G17: =IF(E17="","",E17*F17) | H17: =IF(E17="","",Assumptions!B17) | I17: =IF(G17="","",G17*(1+H17)) | K17: =IF(I17="","",I17*J17)
A18: BB-013 | G18: =IF(E18="","",E18*F18) | H18: =IF(E18="","",Assumptions!B17) | I18: =IF(G18="","",G18*(1+H18)) | K18: =IF(I18="","",I18*J18)
A19: BB-014 | G19: =IF(E19="","",E19*F19) | H19: =IF(E19="","",Assumptions!B17) | I19: =IF(G19="","",G19*(1+H19)) | K19: =IF(I19="","",I19*J19)
A20: BB-015 | G20: =IF(E20="","",E20*F20) | H20: =IF(E20="","",Assumptions!B17) | I20: =IF(G20="","",G20*(1+H20)) | K20: =IF(I20="","",I20*J20)
A21: BB-016 | G21: =IF(E21="","",E21*F21) | H21: =IF(E21="","",Assumptions!B17) | I21: =IF(G21="","",G21*(1+H21)) | K21: =IF(I21="","",I21*J21)
A22: BB-017 | G22: =IF(E22="","",E22*F22) | H22: =IF(E22="","",Assumptions!B17) | I22: =IF(G22="","",G22*(1+H22)) | K22: =IF(I22="","",I22*J22)
A23: BB-018 | G23: =IF(E23="","",E23*F23) | H23: =IF(E23="","",Assumptions!B17) | I23: =IF(G23="","",G23*(1+H23)) | K23: =IF(I23="","",I23*J23)
A24: BB-019 | G24: =IF(E24="","",E24*F24) | H24: =IF(E24="","",Assumptions!B17) | I24: =IF(G24="","",G24*(1+H24)) | K24: =IF(I24="","",I24*J24)
A25: BB-020 | G25: =IF(E25="","",E25*F25) | H25: =IF(E25="","",Assumptions!B17) | I25: =IF(G25="","",G25*(1+H25)) | K25: =IF(I25="","",I25*J25)
A28: BUY-BACK SUMMARY BY PRACTICE
A29: Practice | B29: Applications | C29: Approved Claims (£) | D29: Pending Claims (£) | E29: Total Claimed (£) | F29: SDA Appts Covered/Wk
A30: The Parks MC | B30: =COUNTIF(B6:B25,A30) -> 0 | C30: =SUMIFS(K6:K25,B6:B25,A30,M6:M25,"Approved") -> 0 | D30: =SUMIFS(K6:K25,B6:B25,A30,M6:M25,"Submitted")+SUMIFS(K6:K25,B6:B25,A30,M6:M25,"Under Review")+SUMIFS(K6:K25,B6:B25,A30,M6:M25,"Draft") -> 0 | E30: =C30+D30 -> 0 | F30: =SUMIFS(L6:L25,B6:B25,A30,M6:M25,"Approved") -> 0
A31: Brackley MC | B31: =COUNTIF(B6:B25,A31) -> 0 | C31: =SUMIFS(K6:K25,B6:B25,A31,M6:M25,"Approved") -> 0 | D31: =SUMIFS(K6:K25,B6:B25,A31,M6:M25,"Submitted")+SUMIFS(K6:K25,B6:B25,A31,M6:M25,"Under Review")+SUMIFS(K6:K25,B6:B25,A31,M6:M25,"Draft") -> 0 | E31: =C31+D31 -> 0 | F31: =SUMIFS(L6:L25,B6:B25,A31,M6:M25,"Approved") -> 0
A32: Springfield Surgery | B32: =COUNTIF(B6:B25,A32) -> 0 | C32: =SUMIFS(K6:K25,B6:B25,A32,M6:M25,"Approved") -> 0 | D32: =SUMIFS(K6:K25,B6:B25,A32,M6:M25,"Submitted")+SUMIFS(K6:K25,B6:B25,A32,M6:M25,"Under Review")+SUMIFS(K6:K25,B6:B25,A32,M6:M25,"Draft") -> 0 | E32: =C32+D32 -> 0 | F32: =SUMIFS(L6:L25,B6:B25,A32,M6:M25,"Approved") -> 0
A33: Towcester MC | B33: =COUNTIF(B6:B25,A33) -> 1 | C33: =SUMIFS(K6:K25,B6:B25,A33,M6:M25,"Approved") -> 0 | D33: =SUMIFS(K6:K25,B6:B25,A33,M6:M25,"Submitted")+SUMIFS(K6:K25,B6:B25,A33,M6:M25,"Under Review")+SUMIFS(K6:K25,B6:B25,A33,M6:M25,"Draft") -> 0 | E33: =C33+D33 -> 0 | F33: =SUMIFS(L6:L25,B6:B25,A33,M6:M25,"Approved") -> 0
A34: Bugbrooke Surgery | B34: =COUNTIF(B6:B25,A34) -> 0 | C34: =SUMIFS(K6:K25,B6:B25,A34,M6:M25,"Approved") -> 0 | D34: =SUMIFS(K6:K25,B6:B25,A34,M6:M25,"Submitted")+SUMIFS(K6:K25,B6:B25,A34,M6:M25,"Under Review")+SUMIFS(K6:K25,B6:B25,A34,M6:M25,"Draft") -> 0 | E34: =C34+D34 -> 0 | F34: =SUMIFS(L6:L25,B6:B25,A34,M6:M25,"Approved") -> 0
A35: Brook Health Centre | B35: =COUNTIF(B6:B25,A35) -> 0 | C35: =SUMIFS(K6:K25,B6:B25,A35,M6:M25,"Approved") -> 0 | D35: =SUMIFS(K6:K25,B6:B25,A35,M6:M25,"Submitted")+SUMIFS(K6:K25,B6:B25,A35,M6:M25,"Under Review")+SUMIFS(K6:K25,B6:B25,A35,M6:M25,"Draft") -> 0 | E35: =C35+D35 -> 0 | F35: =SUMIFS(L6:L25,B6:B25,A35,M6:M25,"Approved") -> 0
A36: Denton Village Surgery | B36: =COUNTIF(B6:B25,A36) -> 1 | C36: =SUMIFS(K6:K25,B6:B25,A36,M6:M25,"Approved") -> 0 | D36: =SUMIFS(K6:K25,B6:B25,A36,M6:M25,"Submitted")+SUMIFS(K6:K25,B6:B25,A36,M6:M25,"Under Review")+SUMIFS(K6:K25,B6:B25,A36,M6:M25,"Draft") -> 113854.4 | E36: =C36+D36 -> 113854.4 | F36: =SUMIFS(L6:L25,B6:B25,A36,M6:M25,"Approved") -> 0
A37: TOTAL | B37: =SUM(B30:B36) -> 2 | C37: =SUM(C30:C36) -> 0 | D37: =SUM(D30:D36) -> 113854.4 | E37: =SUM(E30:E36) -> 113854.4 | F37: =SUM(F30:F36) -> 0

Sheet Cash Flow
A1: MONTHLY CONTRACT CASH FLOW & MAX CLAIMABLE VALUE
A2: Contract paid in 12 equal monthly instalments — practices cannot claim more than has been received. Open book.
A4: NEIGHBOURHOOD CASH FLOW (ALL PRACTICES)
A5: Month | B5: Month Name | C5: Monthly Instalment (£) | D5: Cumulative Paid (£) | E5: New SDA Spend (£) | F5: Buy-Back Drawn (£) | G5: Total Claimed (£) | H5: Cumulative Claimed (£) | I5: Remaining Claimable (£) | J5: % Drawn Down
A6: 1 | B6: April | C6: =Assumptions!B8/Assumptions!B18 -> 196562.23 | D6: =C6*A6 -> 196562.23 | G6: =E6+F6 -> 0 | H6: =G6 -> 0 | I6: =D6-H6 -> 196562.23 | J6: =IF(D6>0,H6/D6,0) -> 0
A7: 2 | B7: May | C7: =Assumptions!B8/Assumptions!B18 -> 196562.23 | D7: =C7*A7 -> 393124.45 | G7: =E7+F7 -> 0 | H7: =H6+G7 -> 0 | I7: =D7-H7 -> 393124.45 | J7: =IF(D7>0,H7/D7,0) -> 0
A8: 3 | B8: June | C8: =Assumptions!B8/Assumptions!B18 -> 196562.23 | D8: =C8*A8 -> 589686.68 | G8: =E8+F8 -> 0 | H8: =H7+G8 -> 0 | I8: =D8-H8 -> 589686.68 | J8: =IF(D8>0,H8/D8,0) -> 0
A9: 4 | B9: July | C9: =Assumptions!B8/Assumptions!B18 -> 196562.23 | D9: =C9*A9 -> 786248.91 | G9: =E9+F9 -> 0 | H9: =H8+G9 -> 0 | I9: =D9-H9 -> 786248.91 | J9: =IF(D9>0,H9/D9,0) -> 0
A10: 5 | B10: August | C10: =Assumptions!B8/Assumptions!B18 -> 196562.23 | D10: =C10*A10 -> 982811.13 | G10: =E10+F10 -> 0 | H10: =H9+G10 -> 0 | I10: =D10-H10 -> 982811.13 | J10: =IF(D10>0,H10/D10,0) -> 0
A11: 6 | B11: September | C11: =Assumptions!B8/Assumptions!B18 -> 196562.23 | D11: =C11*A11 -> 1179373.4 | G11: =E11+F11 -> 0 | H11: =H10+G11 -> 0 | I11: =D11-H11 -> 1179373.4 | J11: =IF(D11>0,H11/D11,0) -> 0
A12: 7 | B12: October | C12: =Assumptions!B8/Assumptions!B18 -> 196562.23 | D12: =C12*A12 -> 1375935.6 | G12: =E12+F12 -> 0 | H12: =H11+G12 -> 0 | I12: =D12-H12 -> 1375935.6 | J12: =IF(D12>0,H12/D12,0) -> 0
A13: 8 | B13: November | C13: =Assumptions!B8/Assumptions!B18 -> 196562.23 | D13: =C13*A13 -> 1572497.8 | G13: =E13+F13 -> 0 | H13: =H12+G13 -> 0 | I13: =D13-H13 -> 1572497.8 | J13: =IF(D13>0,H13/D13,0) -> 0
A14: 9 | B14: December | C14: =Assumptions!B8/Assumptions!B18 -> 196562.23 | D14: =C14*A14 -> 1769060 | G14: =E14+F14 -> 0 | H14: =H13+G14 -> 0 | I14: =D14-H14 -> 1769060 | J14: =IF(D14>0,H14/D14,0) -> 0
A15: 10 | B15: January | C15: =Assumptions!B8/Assumptions!B18 -> 196562.23 | D15: =C15*A15 -> 1965622.3 | G15: =E15+F15 -> 0 | H15: =H14+G15 -> 0 | I15: =D15-H15 -> 1965622.3 | J15: =IF(D15>0,H15/D15,0) -> 0
A16: 11 | B16: February | C16: =Assumptions!B8/Assumptions!B18 -> 196562.23 | D16: =C16*A16 -> 2162184.5 | G16: =E16+F16 -> 0 | H16: =H15+G16 -> 0 | I16: =D16-H16 -> 2162184.5 | J16: =IF(D16>0,H16/D16,0) -> 0
A17: 12 | B17: March | C17: =Assumptions!B8/Assumptions!B18 -> 196562.23 | D17: =C17*A17 -> 2358746.7 | G17: =E17+F17 -> 0 | H17: =H16+G17 -> 0 | I17: =D17-H17 -> 2358746.7 | J17: =IF(D17>0,H17/D17,0) -> 0
B18: ANNUAL TOTAL | C18: =SUM(C6:C17) -> 2358746.7 | D18: =D17 -> 2358746.7 | E18: =SUM(E6:E17) -> 0 | F18: =SUM(F6:F17) -> 0 | G18: =SUM(G6:G17) -> 0 | H18: =H17 -> 0 | I18: =I17 -> 2358746.7 | J18: =J17 -> 0
A21: MONTHLY INSTALMENT PER PRACTICE
A22: Practice | B22: Annual Allocation (£) | C22: Monthly Instalment (£) | D22: 3-Month Cumulative (£) | E22: 6-Month Cumulative (£) | F22: 9-Month Cumulative (£) | G22: 12-Month Cumulative (£)
A23: ='Practice Allocations'!A4 -> The Parks MC | B23: ='Practice Allocations'!D4 -> 601034.91 | C23: =B23/12 -> 50086.243 | D23: =C23*3 -> 150258.73 | E23: =C23*6 -> 300517.46 | F23: =C23*9 -> 450776.18 | G23: =B23 -> 601034.91
A24: ='Practice Allocations'!A5 -> Brackley MC | B24: ='Practice Allocations'!D5 -> 426861.96 | C24: =B24/12 -> 35571.83 | D24: =C24*3 -> 106715.49 | E24: =C24*6 -> 213430.98 | F24: =C24*9 -> 320146.47 | G24: =B24 -> 426861.96
A25: ='Practice Allocations'!A6 -> Springfield Surgery | B25: ='Practice Allocations'!D6 -> 332047.63 | C25: =B25/12 -> 27670.636 | D25: =C25*3 -> 83011.908 | E25: =C25*6 -> 166023.82 | F25: =C25*9 -> 249035.72 | G25: =B25 -> 332047.63
A26: ='Practice Allocations'!A7 -> Towcester MC | B26: ='Practice Allocations'!D7 -> 309324.84 | C26: =B26/12 -> 25777.07 | D26: =C26*3 -> 77331.21 | E26: =C26*6 -> 154662.42 | F26: =C26*9 -> 231993.63 | G26: =B26 -> 309324.84
A27: ='Practice Allocations'!A8 -> Bugbrooke Surgery | B27: ='Practice Allocations'!D8 -> 284048.04 | C27: =B27/12 -> 23670.67 | D27: =C27*3 -> 71012.01 | E27: =C27*6 -> 142024.02 | F27: =C27*9 -> 213036.03 | G27: =B27 -> 284048.04
A28: ='Practice Allocations'!A9 -> Brook Health Centre | B28: ='Practice Allocations'!D9 -> 238786.77 | C28: =B28/12 -> 19898.897 | D28: =C28*3 -> 59696.692 | E28: =C28*6 -> 119393.38 | F28: =C28*9 -> 179090.08 | G28: =B28 -> 238786.77
A29: ='Practice Allocations'!A10 -> Denton Village Surgery | B29: ='Practice Allocations'!D10 -> 166642.57 | C29: =B29/12 -> 13886.881 | D29: =C29*3 -> 41660.643 | E29: =C29*6 -> 83321.285 | F29: =C29*9 -> 124981.93 | G29: =B29 -> 166642.57
A30: TOTAL | B30: =SUM(B23:B29) -> 2358746.7 | C30: =SUM(C23:C29) -> 196562.23 | D30: =SUM(D23:D29) -> 589686.68 | E30: =SUM(E23:E29) -> 1179373.4 | F30: =SUM(F23:F29) -> 1769060 | G30: =SUM(G23:G29) -> 2358746.7

Sheet Compliance Tracker
A1: WEEKLY COMPLIANCE TRACKER — ACTUALS VS TARGETS
A2: Enter actual weekly appointments delivered per practice. RAG status auto-calculates. Green ≥100%, Amber ≥80%, Red <80%.
A3: Week | B3: Period | C3: The Parks MC | D3: Brackley MC | E3: Springfield | F3: Towcester MC | G3: Bugbrooke | H3: Brook Health | I3: Denton Village | J3: Total Actual | K3: Total Target | L3: RAG
A4: 1 | B4: Winter | J4: =SUM(C4:I4) -> 0 | K4: =IF(B4="Winter",'Practice Allocations'!J11,'Practice Allocations'!G11) -> 1630.4288 | L4: =IF(J4="","",IF(J4>=K4,"GREEN",IF(J4>=K4*0.8,"AMBER","RED"))) -> RED
A5: 2 | B5: Winter | J5: =SUM(C5:I5) -> 0 | K5: =IF(B5="Winter",'Practice Allocations'!J11,'Practice Allocations'!G11) -> 1630.4288 | L5: =IF(J5="","",IF(J5>=K5,"GREEN",IF(J5>=K5*0.8,"AMBER","RED"))) -> RED
A6: 3 | B6: Winter | J6: =SUM(C6:I6) -> 0 | K6: =IF(B6="Winter",'Practice Allocations'!J11,'Practice Allocations'!G11) -> 1630.4288 | L6: =IF(J6="","",IF(J6>=K6,"GREEN",IF(J6>=K6*0.8,"AMBER","RED"))) -> RED
A7: 4 | B7: Winter | J7: =SUM(C7:I7) -> 0 | K7: =IF(B7="Winter",'Practice Allocations'!J11,'Practice Allocations'!G11) -> 1630.4288 | L7: =IF(J7="","",IF(J7>=K7,"GREEN",IF(J7>=K7*0.8,"AMBER","RED"))) -> RED
A8: 5 | B8: Winter | J8: =SUM(C8:I8) -> 0 | K8: =IF(B8="Winter",'Practice Allocations'!J11,'Practice Allocations'!G11) -> 1630.4288 | L8: =IF(J8="","",IF(J8>=K8,"GREEN",IF(J8>=K8*0.8,"AMBER","RED"))) -> RED
A9: 6 | B9: Winter | J9: =SUM(C9:I9) -> 0 | K9: =IF(B9="Winter",'Practice Allocations'!J11,'Practice Allocations'!G11) -> 1630.4288 | L9: =IF(J9="","",IF(J9>=K9,"GREEN",IF(J9>=K9*0.8,"AMBER","RED"))) -> RED
A10: 7 | B10: Winter | J10: =SUM(C10:I10) -> 0 | K10: =IF(B10="Winter",'Practice Allocations'!J11,'Practice Allocations'!G11) -> 1630.4288 | L10: =IF(J10="","",IF(J10>=K10,"GREEN",IF(J10>=K10*0.8,"AMBER","RED"))) -> RED
A11: 8 | B11: Winter | J11: =SUM(C11:I11) -> 0 | K11: =IF(B11="Winter",'Practice Allocations'!J11,'Practice Allocations'!G11) -> 1630.4288 | L11: =IF(J11="","",IF(J11>=K11,"GREEN",IF(J11>=K11*0.8,"AMBER","RED"))) -> RED
A12: 9 | B12: Winter | J12: =SUM(C12:I12) -> 0 | K12: =IF(B12="Winter",'Practice Allocations'!J11,'Practice Allocations'!G11) -> 1630.4288 | L12: =IF(J12="","",IF(J12>=K12,"GREEN",IF(J12>=K12*0.8,"AMBER","RED"))) -> RED
A13: 10 | B13: Winter | J13: =SUM(C13:I13) -> 0 | K13: =IF(B13="Winter",'Practice Allocations'!J11,'Practice Allocations'!G11) -> 1630.4288 | L13: =IF(J13="","",IF(J13>=K13,"GREEN",IF(J13>=K13*0.8,"AMBER","RED"))) -> RED
A14: 11 | B14: Winter | J14: =SUM(C14:I14) -> 0 | K14: =IF(B14="Winter",'Practice Allocations'!J11,'Practice Allocations'!G11) -> 1630.4288 | L14: =IF(J14="","",IF(J14>=K14,"GREEN",IF(J14>=K14*0.8,"AMBER","RED"))) -> RED
A15: 12 | B15: Winter | J15: =SUM(C15:I15) -> 0 | K15: =IF(B15="Winter",'Practice Allocations'!J11,'Practice Allocations'!G11) -> 1630.4288 | L15: =IF(J15="","",IF(J15>=K15,"GREEN",IF(J15>=K15*0.8,"AMBER","RED"))) -> RED
A16: 13 | B16: Non-Winter | J16: =SUM(C16:I16) -> 0 | K16: =IF(B16="Winter",'Practice Allocations'!J11,'Practice Allocations'!G11) -> 1361.6768 | L16: =IF(J16="","",IF(J16>=K16,"GREEN",IF(J16>=K16*0.8,"AMBER","RED"))) -> RED
A17: 14 | B17: Non-Winter | J17: =SUM(C17:I17) -> 0 | K17: =IF(B17="Winter",'Practice Allocations'!J11,'Practice Allocations'!G11) -> 1361.6768 | L17: =IF(J17="","",IF(J17>=K17,"GREEN",IF(J17>=K17*0.8,"AMBER","RED"))) -> RED
A18: 15 | B18: Non-Winter | J18: =SUM(C18:I18) -> 0 | K18: =IF(B18="Winter",'Practice Allocations'!J11,'Practice Allocations'!G11) -> 1361.6768 | L18: =IF(J18="","",IF(J18>=K18,"GREEN",IF(J18>=K18*0.8,"AMBER","RED"))) -> RED
A19: 16 | B19: Non-Winter | J19: =SUM(C19:I19) -> 0 | K19: =IF(B19="Winter",'Practice Allocations'!J11,'Practice Allocations'!G11) -> 1361.6768 | L19: =IF(J19="","",IF(J19>=K19,"GREEN",IF(J19>=K19*0.8,"AMBER","RED"))) -> RED
A20: 17 | B20: Non-Winter | J20: =SUM(C20:I20) -> 0 | K20: =IF(B20="Winter",'Practice Allocations'!J11,'Practice Allocations'!G11) -> 1361.6768 | L20: =IF(J20="","",IF(J20>=K20,"GREEN",IF(J20>=K20*0.8,"AMBER","RED"))) -> RED
A21: 18 | B21: Non-Winter | J21: =SUM(C21:I21) -> 0 | K21: =IF(B21="Winter",'Practice Allocations'!J11,'Practice Allocations'!G11) -> 1361.6768 | L21: =IF(J21="","",IF(J21>=K21,"GREEN",IF(J21>=K21*0.8,"AMBER","RED"))) -> RED
A22: 19 | B22: Non-Winter | J22: =SUM(C22:I22) -> 0 | K22: =IF(B22="Winter",'Practice Allocations'!J11,'Practice Allocations'!G11) -> 1361.6768 | L22: =IF(J22="","",IF(J22>=K22,"GREEN",IF(J22>=K22*0.8,"AMBER","RED"))) -> RED
A23: 20 | B23: Non-Winter | J23: =SUM(C23:I23) -> 0 | K23: =IF(B23="Winter",'Practice Allocations'!J11,'Practice Allocations'!G11) -> 1361.6768 | L23: =IF(J23="","",IF(J23>=K23,"GREEN",IF(J23>=K23*0.8,"AMBER","RED"))) -> RED
A24: 21 | B24: Non-Winter | J24: =SUM(C24:I24) -> 0 | K24: =IF(B24="Winter",'Practice Allocations'!J11,'Practice Allocations'!G11) -> 1361.6768 | L24: =IF(J24="","",IF(J24>=K24,"GREEN",IF(J24>=K24*0.8,"AMBER","RED"))) -> RED
A25: 22 | B25: Non-Winter | J25: =SUM(C25:I25) -> 0 | K25: =IF(B25="Winter",'Practice Allocations'!J11,'Practice Allocations'!G11) -> 1361.6768 | L25: =IF(J25="","",IF(J25>=K25,"GREEN",IF(J25>=K25*0.8,"AMBER","RED"))) -> RED
A26: 23 | B26: Non-Winter | J26: =SUM(C26:I26) -> 0 | K26: =IF(B26="Winter",'Practice Allocations'!J11,'Practice Allocations'!G11) -> 1361.6768 | L26: =IF(J26="","",IF(J26>=K26,"GREEN",IF(J26>=K26*0.8,"AMBER","RED"))) -> RED
A27: 24 | B27: Non-Winter | J27: =SUM(C27:I27) -> 0 | K27: =IF(B27="Winter",'Practice Allocations'!J11,'Practice Allocations'!G11) -> 1361.6768 | L27: =IF(J27="","",IF(J27>=K27,"GREEN",IF(J27>=K27*0.8,"AMBER","RED"))) -> RED
A28: 25 | B28: Non-Winter | J28: =SUM(C28:I28) -> 0 | K28: =IF(B28="Winter",'Practice Allocations'!J11,'Practice Allocations'!G11) -> 1361.6768 | L28: =IF(J28="","",IF(J28>=K28,"GREEN",IF(J28>=K28*0.8,"AMBER","RED"))) -> RED
A29: 26 | B29: Non-Winter | J29: =SUM(C29:I29) -> 0 | K29: =IF(B29="Winter",'Practice Allocations'!J11,'Practice Allocations'!G11) -> 1361.6768 | L29: =IF(J29="","",IF(J29>=K29,"GREEN",IF(J29>=K29*0.8,"AMBER","RED"))) -> RED
A30: 27 | B30: Non-Winter | J30: =SUM(C30:I30) -> 0 | K30: =IF(B30="Winter",'Practice Allocations'!J11,'Practice Allocations'!G11) -> 1361.6768 | L30: =IF(J30="","",IF(J30>=K30,"GREEN",IF(J30>=K30*0.8,"AMBER","RED"))) -> RED
A31: 28 | B31: Non-Winter | J31: =SUM(C31:I31) -> 0 | K31: =IF(B31="Winter",'Practice Allocations'!J11,'Practice Allocations'!G11) -> 1361.6768 | L31: =IF(J31="","",IF(J31>=K31,"GREEN",IF(J31>=K31*0.8,"AMBER","RED"))) -> RED
A32: 29 | B32: Non-Winter | J32: =SUM(C32:I32) -> 0 | K32: =IF(B32="Winter",'Practice Allocations'!J11,'Practice Allocations'!G11) -> 1361.6768 | L32: =IF(J32="","",IF(J32>=K32,"GREEN",IF(J32>=K32*0.8,"AMBER","RED"))) -> RED
A33: 30 | B33: Non-Winter | J33: =SUM(C33:I33) -> 0 | K33: =IF(B33="Winter",'Practice Allocations'!J11,'Practice Allocations'!G11) -> 1361.6768 | L33: =IF(J33="","",IF(J33>=K33,"GREEN",IF(J33>=K33*0.8,"AMBER","RED"))) -> RED
A34: 31 | B34: Non-Winter | J34: =SUM(C34:I34) -> 0 | K34: =IF(B34="Winter",'Practice Allocations'!J11,'Practice Allocations'!G11) -> 1361.6768 | L34: =IF(J34="","",IF(J34>=K34,"GREEN",IF(J34>=K34*0.8,"AMBER","RED"))) -> RED
A35: 32 | B35: Non-Winter | J35: =SUM(C35:I35) -> 0 | K35: =IF(B35="Winter",'Practice Allocations'!J11,'Practice Allocations'!G11) -> 1361.6768 | L35: =IF(J35="","",IF(J35>=K35,"GREEN",IF(J35>=K35*0.8,"AMBER","RED"))) -> RED
A36: 33 | B36: Non-Winter | J36: =SUM(C36:I36) -> 0 | K36: =IF(B36="Winter",'Practice Allocations'!J11,'Practice Allocations'!G11) -> 1361.6768 | L36: =IF(J36="","",IF(J36>=K36,"GREEN",IF(J36>=K36*0.8,"AMBER","RED"))) -> RED
A37: 34 | B37: Non-Winter | J37: =SUM(C37:I37) -> 0 | K37: =IF(B37="Winter",'Practice Allocations'!J11,'Practice Allocations'!G11) -> 1361.6768 | L37: =IF(J37="","",IF(J37>=K37,"GREEN",IF(J37>=K37*0.8,"AMBER","RED"))) -> RED
A38: 35 | B38: Non-Winter | J38: =SUM(C38:I38) -> 0 | K38: =IF(B38="Winter",'Practice Allocations'!J11,'Practice Allocations'!G11) -> 1361.6768 | L38: =IF(J38="","",IF(J38>=K38,"GREEN",IF(J38>=K38*0.8,"AMBER","RED"))) -> RED
A39: 36 | B39: Non-Winter | J39: =SUM(C39:I39) -> 0 | K39: =IF(B39="Winter",'Practice Allocations'!J11,'Practice Allocations'!G11) -> 1361.6768 | L39: =IF(J39="","",IF(J39>=K39,"GREEN",IF(J39>=K39*0.8,"AMBER","RED"))) -> RED
A40: 37 | B40: Non-Winter | J40: =SUM(C40:I40) -> 0 | K40: =IF(B40="Winter",'Practice Allocations'!J11,'Practice Allocations'!G11) -> 1361.6768 | L40: =IF(J40="","",IF(J40>=K40,"GREEN",IF(J40>=K40*0.8,"AMBER","RED"))) -> RED
A41: 38 | B41: Non-Winter | J41: =SUM(C41:I41) -> 0 | K41: =IF(B41="Winter",'Practice Allocations'!J11,'Practice Allocations'!G11) -> 1361.6768 | L41: =IF(J41="","",IF(J41>=K41,"GREEN",IF(J41>=K41*0.8,"AMBER","RED"))) -> RED
A42: 39 | B42: Non-Winter | J42: =SUM(C42:I42) -> 0 | K42: =IF(B42="Winter",'Practice Allocations'!J11,'Practice Allocations'!G11) -> 1361.6768 | L42: =IF(J42="","",IF(J42>=K42,"GREEN",IF(J42>=K42*0.8,"AMBER","RED"))) -> RED
A43: 40 | B43: Non-Winter | J43: =SUM(C43:I43) -> 0 | K43: =IF(B43="Winter",'Practice Allocations'!J11,'Practice Allocations'!G11) -> 1361.6768 | L43: =IF(J43="","",IF(J43>=K43,"GREEN",IF(J43>=K43*0.8,"AMBER","RED"))) -> RED
A44: 41 | B44: Non-Winter | J44: =SUM(C44:I44) -> 0 | K44: =IF(B44="Winter",'Practice Allocations'!J11,'Practice Allocations'!G11) -> 1361.6768 | L44: =IF(J44="","",IF(J44>=K44,"GREEN",IF(J44>=K44*0.8,"AMBER","RED"))) -> RED
A45: 42 | B45: Non-Winter | J45: =SUM(C45:I45) -> 0 | K45: =IF(B45="Winter",'Practice Allocations'!J11,'Practice Allocations'!G11) -> 1361.6768 | L45: =IF(J45="","",IF(J45>=K45,"GREEN",IF(J45>=K45*0.8,"AMBER","RED"))) -> RED
A46: 43 | B46: Non-Winter | J46: =SUM(C46:I46) -> 0 | K46: =IF(B46="Winter",'Practice Allocations'!J11,'Practice Allocations'!G11) -> 1361.6768 | L46: =IF(J46="","",IF(J46>=K46,"GREEN",IF(J46>=K46*0.8,"AMBER","RED"))) -> RED
A47: 44 | B47: Winter | J47: =SUM(C47:I47) -> 0 | K47: =IF(B47="Winter",'Practice Allocations'!J11,'Practice Allocations'!G11) -> 1630.4288 | L47: =IF(J47="","",IF(J47>=K47,"GREEN",IF(J47>=K47*0.8,"AMBER","RED"))) -> RED
A48: 45 | B48: Winter | J48: =SUM(C48:I48) -> 0 | K48: =IF(B48="Winter",'Practice Allocations'!J11,'Practice Allocations'!G11) -> 1630.4288 | L48: =IF(J48="","",IF(J48>=K48,"GREEN",IF(J48>=K48*0.8,"AMBER","RED"))) -> RED
A49: 46 | B49: Winter | J49: =SUM(C49:I49) -> 0 | K49: =IF(B49="Winter",'Practice Allocations'!J11,'Practice Allocations'!G11) -> 1630.4288 | L49: =IF(J49="","",IF(J49>=K49,"GREEN",IF(J49>=K49*0.8,"AMBER","RED"))) -> RED
A50: 47 | B50: Winter | J50: =SUM(C50:I50) -> 0 | K50: =IF(B50="Winter",'Practice Allocations'!J11,'Practice Allocations'!G11) -> 1630.4288 | L50: =IF(J50="","",IF(J50>=K50,"GREEN",IF(J50>=K50*0.8,"AMBER","RED"))) -> RED
A51: 48 | B51: Winter | J51: =SUM(C51:I51) -> 0 | K51: =IF(B51="Winter",'Practice Allocations'!J11,'Practice Allocations'!G11) -> 1630.4288 | L51: =IF(J51="","",IF(J51>=K51,"GREEN",IF(J51>=K51*0.8,"AMBER","RED"))) -> RED
A52: 49 | B52: Winter | J52: =SUM(C52:I52) -> 0 | K52: =IF(B52="Winter",'Practice Allocations'!J11,'Practice Allocations'!G11) -> 1630.4288 | L52: =IF(J52="","",IF(J52>=K52,"GREEN",IF(J52>=K52*0.8,"AMBER","RED"))) -> RED
A53: 50 | B53: Winter | J53: =SUM(C53:I53) -> 0 | K53: =IF(B53="Winter",'Practice Allocations'!J11,'Practice Allocations'!G11) -> 1630.4288 | L53: =IF(J53="","",IF(J53>=K53,"GREEN",IF(J53>=K53*0.8,"AMBER","RED"))) -> RED
A54: 51 | B54: Winter | J54: =SUM(C54:I54) -> 0 | K54: =IF(B54="Winter",'Practice Allocations'!J11,'Practice Allocations'!G11) -> 1630.4288 | L54: =IF(J54="","",IF(J54>=K54,"GREEN",IF(J54>=K54*0.8,"AMBER","RED"))) -> RED
A55: 52 | B55: Winter | J55: =SUM(C55:I55) -> 0 | K55: =IF(B55="Winter",'Practice Allocations'!J11,'Practice Allocations'!G11) -> 1630.4288 | L55: =IF(J55="","",IF(J55>=K55,"GREEN",IF(J55>=K55*0.8,"AMBER","RED"))) -> RED

Sheet Workforce
A1: SDA WORKFORCE DIRECTORY
A3: Staff Name | B3: Role | C3: Home Practice | D3: Contract Type | E3: Sessions/Wk | F3: Cost/Session (£) | G3: Annual Cost (£) | H3: On-Costs (£) | I3: Total Cost (£) | J3: Works At (Sites) | K3: Available Days | L3: Notes
G4: =IF(E4="","",E4*F4) | H4: =IF(G4="","",G4*Assumptions!B17) | I4: =IF(G4="","",G4+H4)
G5: =IF(E5="","",E5*F5) | H5: =IF(G5="","",G5*Assumptions!B17) | I5: =IF(G5="","",G5+H5)
G6: =IF(E6="","",E6*F6) | H6: =IF(G6="","",G6*Assumptions!B17) | I6: =IF(G6="","",G6+H6)
G7: =IF(E7="","",E7*F7) | H7: =IF(G7="","",G7*Assumptions!B17) | I7: =IF(G7="","",G7+H7)
G8: =IF(E8="","",E8*F8) | H8: =IF(G8="","",G8*Assumptions!B17) | I8: =IF(G8="","",G8+H8)
G9: =IF(E9="","",E9*F9) | H9: =IF(G9="","",G9*Assumptions!B17) | I9: =IF(G9="","",G9+H9)
G10: =IF(E10="","",E10*F10) | H10: =IF(G10="","",G10*Assumptions!B17) | I10: =IF(G10="","",G10+H10)
G11: =IF(E11="","",E11*F11) | H11: =IF(G11="","",G11*Assumptions!B17) | I11: =IF(G11="","",G11+H11)
G12: =IF(E12="","",E12*F12) | H12: =IF(G12="","",G12*Assumptions!B17) | I12: =IF(G12="","",G12+H12)
G13: =IF(E13="","",E13*F13) | H13: =IF(G13="","",G13*Assumptions!B17) | I13: =IF(G13="","",G13+H13)
G14: =IF(E14="","",E14*F14) | H14: =IF(G14="","",G14*Assumptions!B17) | I14: =IF(G14="","",G14+H14)
G15: =IF(E15="","",E15*F15) | H15: =IF(G15="","",G15*Assumptions!B17) | I15: =IF(G15="","",G15+H15)
G16: =IF(E16="","",E16*F16) | H16: =IF(G16="","",G16*Assumptions!B17) | I16: =IF(G16="","",G16+H16)
G17: =IF(E17="","",E17*F17) | H17: =IF(G17="","",G17*Assumptions!B17) | I17: =IF(G17="","",G17+H17)
G18: =IF(E18="","",E18*F18) | H18: =IF(G18="","",G18*Assumptions!B17) | I18: =IF(G18="","",G18+H18)
G19: =IF(E19="","",E19*F19) | H19: =IF(G19="","",G19*Assumptions!B17) | I19: =IF(G19="","",G19+H19)
G20: =IF(E20="","",E20*F20) | H20: =IF(G20="","",G20*Assumptions!B17) | I20: =IF(G20="","",G20+H20)
G21: =IF(E21="","",E21*F21) | H21: =IF(G21="","",G21*Assumptions!B17) | I21: =IF(G21="","",G21+H21)
G22: =IF(E22="","",E22*F22) | H22: =IF(G22="","",G22*Assumptions!B17) | I22: =IF(G22="","",G22+H22)
G23: =IF(E23="","",E23*F23) | H23: =IF(G23="","",G23*Assumptions!B17) | I23: =IF(G23="","",G23+H23)
G24: =IF(E24="","",E24*F24) | H24: =IF(G24="","",G24*Assumptions!B17) | I24: =IF(G24="","",G24+H24)
G25: =IF(E25="","",E25*F25) | H25: =IF(G25="","",G25*Assumptions!B17) | I25: =IF(G25="","",G25+H25)
G26: =IF(E26="","",E26*F26) | H26: =IF(G26="","",G26*Assumptions!B17) | I26: =IF(G26="","",G26+H26)
G27: =IF(E27="","",E27*F27) | H27: =IF(G27="","",G27*Assumptions!B17) | I27: =IF(G27="","",G27+H27)
G28: =IF(E28="","",E28*F28) | H28: =IF(G28="","",G28*Assumptions!B17) | I28: =IF(G28="","",G28+H28)
G29: =IF(E29="","",E29*F29) | H29: =IF(G29="","",G29*Assumptions!B17) | I29: =IF(G29="","",G29+H29)
G30: =IF(E30="","",E30*F30) | H30: =IF(G30="","",G30*Assumptions!B17) | I30: =IF(G30="","",G30+H30)
G31: =IF(E31="","",E31*F31) | H31: =IF(G31="","",G31*Assumptions!B17) | I31: =IF(G31="","",G31+H31)
G32: =IF(E32="","",E32*F32) | H32: =IF(G32="","",G32*Assumptions!B17) | I32: =IF(G32="","",G32+H32)
G33: =IF(E33="","",E33*F33) | H33: =IF(G33="","",G33*Assumptions!B17) | I33: =IF(G33="","",G33+H33)
A34: TOTAL WORKFORCE COST | E34: =SUM(E4:E33) -> 0 | G34: =SUM(G4:G33) -> 0 | H34: =SUM(H4:H33) -> 0 | I34: =SUM(I4:I33) -> 0

Sheet Practice Contacts
A1: PRACTICE EMAIL CONTACTS — FOR AUTOMATED REPORTS
A2: Maintain email contacts per practice for scheduled report distribution
A3: Practice | B3: Contact Name | C3: Email | D3: Role | E3: Primary? | F3: Weekly Report | G3: Monthly Report | H3: Alerts | I3: Notes
A4: The Parks MC
A5: The Parks MC
A6: The Parks MC
A7: The Parks MC
A8: The Parks MC
A9: Brackley MC
A10: Brackley MC
A11: Brackley MC
A12: Brackley MC
A13: Brackley MC
A14: Springfield Surgery
A15: Springfield Surgery
... A39: BOARD & ICB CONTACTS
A40: NRES Board / ICB | B40: Dr Mark Gray | D40: SNO / Clinical Lead
A41: NRES Board / ICB | B41: Malcolm Railson | D41: Digital & Transformation Lead
A42: NRES Board / ICB | B42: Amanda Palin | D42: Joint Practice Rep
A43: NRES Board / ICB | B43: Dr Simon Ellis | D43: Board Chair / GP Partner
A44: NRES Board / ICB | B44: ICB Finance Contact
A45: NRES Board / ICB | B45: ICB Programme Lead

Sheet Monthly Rota
A1: MONTHLY ROTA OVERVIEW — PRACTICE VIEW
A2: Month: | B2: April 2026 | C2: Practice: | D2: ALL
A4: MONTHLY PLANNING GRID
A5: Week | B5: Mon | C5: Tue | D5: Wed | E5: Thu | F5: Fri | G5: Sat | H5: Weekly Total
A6: Week 1 — Sessions | H6: =SUM(B6:G6) -> 0
A7: Appointments | H7: =SUM(B7:G7) -> 0
A8: — New SDA | H8: =SUM(B8:G8) -> 0
A9: — Buy-Back | H9: =SUM(B9:G9) -> 0
A10: Week 2 — Sessions | H10: =SUM(B10:G10) -> 0
A11: Appointments | H11: =SUM(B11:G11) -> 0
A12: — New SDA | H12: =SUM(B12:G12) -> 0
A13: — Buy-Back | H13: =SUM(B13:G13) -> 0
A14: Week 3 — Sessions | H14: =SUM(B14:G14) -> 0
A15: Appointments | H15: =SUM(B15:G15) -> 0
A16: — New SDA | H16: =SUM(B16:G16) -> 0
A17: — Buy-Back | H17: =SUM(B17:G17) -> 0
... A25: — Buy-Back | H25: =SUM(B25:G25) -> 0
A27: MONTHLY SUMMARY
A28: Total Sessions (Month) | B28: =H6+H10+H14+H18+H22 -> 0
A29: Total Appointments (Month) | B29: =H7+H11+H15+H19+H23 -> 0
A30: New SDA Appointments | B30: =H8+H12+H16+H20+H24 -> 0
A31: Buy-Back Appointments | B31: =H9+H13+H17+H21+H25 -> 0
A32: Monthly Target (approx) | B32: ='Practice Allocations'!G11*4.33 -> 5896.0605
A33: Variance | B33: =B29-B32 -> -5896.0605

Sheet Audit Log
A1: AUDIT TRAIL — CHANGE LOG
A2: Record all changes for governance. Managed by Super Users (Malcolm & Amanda). Immutable once entered.
A3: Date | B3: Changed By | C3: Role | D3: Practice Affected | E3: What Changed | F3: Previous Value | G3: New Value | H3: On Behalf Of

Sheet Parks
A1: The Parks MC — NRES SDA PRACTICE DASHBOARD
A2: Complete view: contract allocation, targets, actuals, workforce, buy-back, cash flow & compliance
A4: PRACTICE PROFILE
A5: Practice Name | B5: =Assumptions!A29 -> The Parks MC
A6: List Size | B6: =Assumptions!B29 -> 22827
A7: Hub / Spoke | B7: HUB
A8: Clinical System | B8: SystmOne
A9: % of Neighbourhood | B9: =Assumptions!E29 -> 0.25481113
A11: CONTRACT ALLOCATION (OPEN BOOK)
A12: Metric | B12: Value
A13: Annual Allocation | B13: ='Practice Allocations'!D4 -> 601034.91
A14: Monthly Instalment (1/12th) | B14: ='Practice Allocations'!E4 -> 50086.243
A15: Recruitment Budget (75%) | B15: ='Practice Allocations'!F4 -> 450776.18
A16: Overheads (25%) | B16: ='Practice Allocations'!D4*Assumptions!B16 -> 150258.73
A18: WEEKLY APPOINTMENT TARGETS
A19: Period | B19: Weeks | C19: Target/Wk | D19: F2F (50%) | E19: Remote (50%) | F19: Seasonal Total
A20: Non-Winter | B20: =Assumptions!B10 -> 39 | C20: ='Practice Allocations'!G4 -> 346.9704 | D20: ='Practice Allocations'!H4 -> 173.4852 | E20: ='Practice Allocations'!I4 -> 173.4852 | F20: =B20*C20 -> 13531.846
A21: Winter | B21: =Assumptions!B11 -> 13 | C21: ='Practice Allocations'!J4 -> 415.4514 | D21: ='Practice Allocations'!K4 -> 207.7257 | E21: ='Practice Allocations'!L4 -> 207.7257 | F21: =B21*C21 -> 5400.8682
A22: ANNUAL TOTAL | B22: =B20+B21 -> 52 | F22: ='Practice Allocations'!M4 -> 18932.714
A24: WEEKLY ACTUALS vs TARGETS (FIRST 13 WEEKS — ADD MORE AS NEEDED)
A25: Week | B25: Period | C25: Target | D25: F2F Actual | E25: Remote Actual | F25: Total Actual | G25: Variance | H25: % Achieved | I25: New SDA | J25: Buy-Back
A26: 1 | B26: Non-Winter | C26: =C20 -> 346.9704 | F26: =D26+E26 -> 0 | G26: =F26-C26 -> -346.9704 | H26: =IF(C26>0,F26/C26,0) -> 0
A27: 2 | B27: Non-Winter | C27: =C20 -> 346.9704 | F27: =D27+E27 -> 0 | G27: =F27-C27 -> -346.9704 | H27: =IF(C27>0,F27/C27,0) -> 0
A28: 3 | B28: Non-Winter | C28: =C20 -> 346.9704 | F28: =D28+E28 -> 0 | G28: =F28-C28 -> -346.9704 | H28: =IF(C28>0,F28/C28,0) -> 0
A29: 4 | B29: Non-Winter | C29: =C20 -> 346.9704 | F29: =D29+E29 -> 0 | G29: =F29-C29 -> -346.9704 | H29: =IF(C29>0,F29/C29,0) -> 0
A30: 5 | B30: Non-Winter | C30: =C20 -> 346.9704 | F30: =D30+E30 -> 0 | G30: =F30-C30 -> -346.9704 | H30: =IF(C30>0,F30/C30,0) -> 0
A31: 6 | B31: Non-Winter | C31: =C20 -> 346.9704 | F31: =D31+E31 -> 0 | G31: =F31-C31 -> -346.9704 | H31: =IF(C31>0,F31/C31,0) -> 0
A32: 7 | B32: Non-Winter | C32: =C20 -> 346.9704 | F32: =D32+E32 -> 0 | G32: =F32-C32 -> -346.9704 | H32: =IF(C32>0,F32/C32,0) -> 0
A33: 8 | B33: Non-Winter | C33: =C20 -> 346.9704 | F33: =D33+E33 -> 0 | G33: =F33-C33 -> -346.9704 | H33: =IF(C33>0,F33/C33,0) -> 0
A34: 9 | B34: Non-Winter | C34: =C20 -> 346.9704 | F34: =D34+E34 -> 0 | G34: =F34-C34 -> -346.9704 | H34: =IF(C34>0,F34/C34,0) -> 0
A35: 10 | B35: Non-Winter | C35: =C20 -> 346.9704 | F35: =D35+E35 -> 0 | G35: =F35-C35 -> -346.9704 | H35: =IF(C35>0,F35/C35,0) -> 0
A36: 11 | B36: Non-Winter | C36: =C20 -> 346.9704 | F36: =D36+E36 -> 0 | G36: =F36-C36 -> -346.9704 | H36: =IF(C36>0,F36/C36,0) -> 0
A37: 12 | B37: Non-Winter | C37: =C20 -> 346.9704 | F37: =D37+E37 -> 0 | G37: =F37-C37 -> -346.9704 | H37: =IF(C37>0,F37/C37,0) -> 0
A38: 13 | B38: Non-Winter | C38: =C20 -> 346.9704 | F38: =D38+E38 -> 0 | G38: =F38-C38 -> -346.9704 | H38: =IF(C38>0,F38/C38,0) -> 0
A39: TOTAL (Wks 1-13) | C39: =SUM(C26:C38) -> 4510.6152 | D39: =SUM(D26:D38) -> 0 | E39: =SUM(E26:E38) -> 0 | F39: =SUM(F26:F38) -> 0 | G39: =F39-C39 -> -4510.6152 | H39: =IF(C39>0,F39/C39,0) -> 0 | I39: =SUM(I26:I38) -> 0 | J39: =SUM(J26:J38) -> 0
A40: RAG Status | B40: =IF(H39>=1,"GREEN",IF(H39>=0.8,"AMBER","RED")) -> RED
A42: STAFF DEPLOYED AT THIS PRACTICE
A43: Staff Name | B43: Role | C43: Contract Type | D43: Sessions/Wk | E43: Appts/Session | F43: Appts/Wk | G43: Cost/Session (£) | H43: Annual Cost (£) | I43: On-Costs (£) | J43: Total (£)
F44: =IF(D44="","",D44*E44) | H44: =IF(D44="","",D44*G44) | I44: =IF(H44="","",H44*Assumptions!B17) | J44: =IF(H44="","",H44+I44)
F45: =IF(D45="","",D45*E45) | H45: =IF(D45="","",D45*G45) | I45: =IF(H45="","",H45*Assumptions!B17) | J45: =IF(H45="","",H45+I45)
F46: =IF(D46="","",D46*E46) | H46: =IF(D46="","",D46*G46) | I46: =IF(H46="","",H46*Assumptions!B17) | J46: =IF(H46="","",H46+I46)
F47: =IF(D47="","",D47*E47) | H47: =IF(D47="","",D47*G47) | I47: =IF(H47="","",H47*Assumptions!B17) | J47: =IF(H47="","",H47+I47)
F48: =IF(D48="","",D48*E48) | H48: =IF(D48="","",D48*G48) | I48: =IF(H48="","",H48*Assumptions!B17) | J48: =IF(H48="","",H48+I48)
F49: =IF(D49="","",D49*E49) | H49: =IF(D49="","",D49*G49) | I49: =IF(H49="","",H49*Assumptions!B17) | J49: =IF(H49="","",H49+I49)
F50: =IF(D50="","",D50*E50) | H50: =IF(D50="","",D50*G50) | I50: =IF(H50="","",H50*Assumptions!B17) | J50: =IF(H50="","",H50+I50)
F51: =IF(D51="","",D51*E51) | H51: =IF(D51="","",D51*G51) | I51: =IF(H51="","",H51*Assumptions!B17) | J51: =IF(H51="","",H51+I51)
F52: =IF(D52="","",D52*E52) | H52: =IF(D52="","",D52*G52) | I52: =IF(H52="","",H52*Assumptions!B17) | J52: =IF(H52="","",H52+I52)
F53: =IF(D53="","",D53*E53) | H53: =IF(D53="","",D53*G53) | I53: =IF(H53="","",H53*Assumptions!B17) | J53: =IF(H53="","",H53+I53)
A54: TOTAL STAFF COST | D54: =SUM(D44:D53) -> 0 | F54: =SUM(F44:F53) -> 0 | H54: =SUM(H44:H53) -> 0 | I54: =SUM(I44:I53) -> 0 | J54: =SUM(J44:J53) -> 0
A56: BUY-BACK APPLICATIONS FOR THIS PRACTICE
A57: Staff Name | B57: Role | C57: Sessions/Wk | D57: Rate/Session (£) | E57: Annual (£) | F57: On-Costs (£) | G57: Total inc OC (£) | H57: Same-Day % | I57: Claim Value (£) | J57: Status
E58: =IF(C58="","",C58*D58) | F58: =IF(E58="","",E58*Assumptions!B17) | G58: =IF(E58="","",E58+F58) | I58: =IF(G58="","",G58*H58)
E59: =IF(C59="","",C59*D59) | F59: =IF(E59="","",E59*Assumptions!B17) | G59: =IF(E59="","",E59+F59) | I59: =IF(G59="","",G59*H59)
E60: =IF(C60="","",C60*D60) | F60: =IF(E60="","",E60*Assumptions!B17) | G60: =IF(E60="","",E60+F60) | I60: =IF(G60="","",G60*H60)
E61: =IF(C61="","",C61*D61) | F61: =IF(E61="","",E61*Assumptions!B17) | G61: =IF(E61="","",E61+F61) | I61: =IF(G61="","",G61*H61)
E62: =IF(C62="","",C62*D62) | F62: =IF(E62="","",E62*Assumptions!B17) | G62: =IF(E62="","",E62+F62) | I62: =IF(G62="","",G62*H62)
A63: TOTAL BUY-BACK | C63: =SUM(C58:C62) -> 0 | E63: =SUM(E58:E62) -> 0 | F63: =SUM(F58:F62) -> 0 | G63: =SUM(G58:G62) -> 0 | I63: =SUM(I58:I62) -> 0
A65: MONTHLY CASH FLOW — THIS PRACTICE (OPEN BOOK)
A66: Month | B66: Instalment (£) | C66: Cumul. Paid (£) | D66: New SDA Spend (£) | E66: Buy-Back Drawn (£) | F66: Total Claimed (£) | G66: Cumul. Claimed (£) | H66: Headroom (£) | I66: % Drawn | J66: RAG
A67: April | B67: ='Practice Allocations'!E4 -> 50086.243 | C67: =B67*1 -> 50086.243 | F67: =D67+E67 -> 0 | G67: =F67 -> 0 | H67: =C67-G67 -> 50086.243 | I67: =IF(C67>0,G67/C67,0) -> 0 | J67: =IF(H67<0,"OVERSPEND",IF(I67>0.9,"HIGH","OK")) -> OK
A68: May | B68: ='Practice Allocations'!E4 -> 50086.243 | C68: =B68*2 -> 100172.49 | F68: =D68+E68 -> 0 | G68: =G67+F68 -> 0 | H68: =C68-G68 -> 100172.49 | I68: =IF(C68>0,G68/C68,0) -> 0 | J68: =IF(H68<0,"OVERSPEND",IF(I68>0.9,"HIGH","OK")) -> OK
A69: June | B69: ='Practice Allocations'!E4 -> 50086.243 | C69: =B69*3 -> 150258.73 | F69: =D69+E69 -> 0 | G69: =G68+F69 -> 0 | H69: =C69-G69 -> 150258.73 | I69: =IF(C69>0,G69/C69,0) -> 0 | J69: =IF(H69<0,"OVERSPEND",IF(I69>0.9,"HIGH","OK")) -> OK
A70: July | B70: ='Practice Allocations'!E4 -> 50086.243 | C70: =B70*4 -> 200344.97 | F70: =D70+E70 -> 0 | G70: =G69+F70 -> 0 | H70: =C70-G70 -> 200344.97 | I70: =IF(C70>0,G70/C70,0) -> 0 | J70: =IF(H70<0,"OVERSPEND",IF(I70>0.9,"HIGH","OK")) -> OK
A71: August | B71: ='Practice Allocations'!E4 -> 50086.243 | C71: =B71*5 -> 250431.21 | F71: =D71+E71 -> 0 | G71: =G70+F71 -> 0 | H71: =C71-G71 -> 250431.21 | I71: =IF(C71>0,G71/C71,0) -> 0 | J71: =IF(H71<0,"OVERSPEND",IF(I71>0.9,"HIGH","OK")) -> OK
A72: September | B72: ='Practice Allocations'!E4 -> 50086.243 | C72: =B72*6 -> 300517.46 | F72: =D72+E72 -> 0 | G72: =G71+F72 -> 0 | H72: =C72-G72 -> 300517.46 | I72: =IF(C72>0,G72/C72,0) -> 0 | J72: =IF(H72<0,"OVERSPEND",IF(I72>0.9,"HIGH","OK")) -> OK
A73: October | B73: ='Practice Allocations'!E4 -> 50086.243 | C73: =B73*7 -> 350603.7 | F73: =D73+E73 -> 0 | G73: =G72+F73 -> 0 | H73: =C73-G73 -> 350603.7 | I73: =IF(C73>0,G73/C73,0) -> 0 | J73: =IF(H73<0,"OVERSPEND",IF(I73>0.9,"HIGH","OK")) -> OK
A74: November | B74: ='Practice Allocations'!E4 -> 50086.243 | C74: =B74*8 -> 400689.94 | F74: =D74+E74 -> 0 | G74: =G73+F74 -> 0 | H74: =C74-G74 -> 400689.94 | I74: =IF(C74>0,G74/C74,0) -> 0 | J74: =IF(H74<0,"OVERSPEND",IF(I74>0.9,"HIGH","OK")) -> OK
A75: December | B75: ='Practice Allocations'!E4 -> 50086.243 | C75: =B75*9 -> 450776.18 | F75: =D75+E75 -> 0 | G75: =G74+F75 -> 0 | H75: =C75-G75 -> 450776.18 | I75: =IF(C75>0,G75/C75,0) -> 0 | J75: =IF(H75<0,"OVERSPEND",IF(I75>0.9,"HIGH","OK")) -> OK
A76: January | B76: ='Practice Allocations'!E4 -> 50086.243 | C76: =B76*10 -> 500862.42 | F76: =D76+E76 -> 0 | G76: =G75+F76 -> 0 | H76: =C76-G76 -> 500862.42 | I76: =IF(C76>0,G76/C76,0) -> 0 | J76: =IF(H76<0,"OVERSPEND",IF(I76>0.9,"HIGH","OK")) -> OK
A77: February | B77: ='Practice Allocations'!E4 -> 50086.243 | C77: =B77*11 -> 550948.67 | F77: =D77+E77 -> 0 | G77: =G76+F77 -> 0 | H77: =C77-G77 -> 550948.67 | I77: =IF(C77>0,G77/C77,0) -> 0 | J77: =IF(H77<0,"OVERSPEND",IF(I77>0.9,"HIGH","OK")) -> OK
A78: March | B78: ='Practice Allocations'!E4 -> 50086.243 | C78: =B78*12 -> 601034.91 | F78: =D78+E78 -> 0 | G78: =G77+F78 -> 0 | H78: =C78-G78 -> 601034.91 | I78: =IF(C78>0,G78/C78,0) -> 0 | J78: =IF(H78<0,"OVERSPEND",IF(I78>0.9,"HIGH","OK")) -> OK
A79: ANNUAL | B79: =SUM(B67:B78) -> 601034.91 | C79: =C78 -> 601034.91 | D79: =SUM(D67:D78) -> 0 | E79: =SUM(E67:E78) -> 0 | F79: =SUM(F67:F78) -> 0 | G79: =G78 -> 0 | H79: =H78 -> 601034.91 | I79: =I78 -> 0
A81: COMPLIANCE SUMMARY
A82: Annual appointment target | B82: =F22 -> 18932.714
A83: Appointments delivered YTD | B83: =F39 -> 0
A84: % of annual target achieved | B84: =IF(B82>0,B83/B82,0) -> 0
A85: Average weekly delivery (first 13 wks) | B85: =IF(COUNTA(F26:F38)>0,AVERAGE(F26:F38),0) -> 0
A86: Non-winter weekly target | B86: =C20 -> 346.9704
A87: Variance (avg vs target) | B87: =B85-B86 -> -346.9704
A88: Remote % (of total delivered) | B88: =IF(F39>0,E39/F39,0) -> 0
A89: Remote % compliant? (≥50%) | B89: =IF(B90>=0.5,"YES — Compliant","NO — Below 50%") -> NO — Below 50%
A90: Total workforce cost (this practice) | B90: =J54 -> 0
A91: Total buy-back claims | B91: =I63 -> 0
A92: Total expenditure (staff + buy-back) | B92: =B90+B91 -> 0
A93: Budget remaining | B93: ='Practice Allocations'!D4-B94 -> 601034.91
A95: REINVESTMENT TRACKING (BUY-BACK PRACTICES ONLY)
A96: Buy-Back Ref | B96: Reinvestment Plan | C96: New Role Recruited | D96: Salary (£) | E96: Start Date | F96: Status | G96: Evidence
A103: PRACTICE NOTES & ACTIONS
A104: Date | B104: Note / Action | C104: Owner | D104: Status | E104: Due Date

Sheet Brackley
A1: Brackley MC — NRES SDA PRACTICE DASHBOARD
A2: Complete view: contract allocation, targets, actuals, workforce, buy-back, cash flow & compliance
A4: PRACTICE PROFILE
A5: Practice Name | B5: =Assumptions!A30 -> Brackley MC
A6: List Size | B6: =Assumptions!B30 -> 16212
A7: Hub / Spoke | B7: HUB
A8: Clinical System | B8: SystmOne
A9: % of Neighbourhood | B9: =Assumptions!E30 -> 0.18096982
A11: CONTRACT ALLOCATION (OPEN BOOK)
A12: Metric | B12: Value
A13: Annual Allocation | B13: ='Practice Allocations'!D5 -> 426861.96
A14: Monthly Instalment (1/12th) | B14: ='Practice Allocations'!E5 -> 35571.83
A15: Recruitment Budget (75%) | B15: ='Practice Allocations'!F5 -> 320146.47
A16: Overheads (25%) | B16: ='Practice Allocations'!D5*Assumptions!B16 -> 106715.49
A18: WEEKLY APPOINTMENT TARGETS
A19: Period | B19: Weeks | C19: Target/Wk | D19: F2F (50%) | E19: Remote (50%) | F19: Seasonal Total
A20: Non-Winter | B20: =Assumptions!B10 -> 39 | C20: ='Practice Allocations'!G5 -> 246.4224 | D20: ='Practice Allocations'!H5 -> 123.2112 | E20: ='Practice Allocations'!I5 -> 123.2112 | F20: =B20*C20 -> 9610.4736
A21: Winter | B21: =Assumptions!B11 -> 13 | C21: ='Practice Allocations'!J5 -> 295.0584 | D21: ='Practice Allocations'!K5 -> 147.5292 | E21: ='Practice Allocations'!L5 -> 147.5292 | F21: =B21*C21 -> 3835.7592
A22: ANNUAL TOTAL | B22: =B20+B21 -> 52 | F22: ='Practice Allocations'!M5 -> 13446.233
A24: WEEKLY ACTUALS vs TARGETS (FIRST 13 WEEKS — ADD MORE AS NEEDED)
A25: Week | B25: Period | C25: Target | D25: F2F Actual | E25: Remote Actual | F25: Total Actual | G25: Variance | H25: % Achieved | I25: New SDA | J25: Buy-Back
A26: 1 | B26: Non-Winter | C26: =C20 -> 246.4224 | F26: =D26+E26 -> 0 | G26: =F26-C26 -> -246.4224 | H26: =IF(C26>0,F26/C26,0) -> 0
A27: 2 | B27: Non-Winter | C27: =C20 -> 246.4224 | F27: =D27+E27 -> 0 | G27: =F27-C27 -> -246.4224 | H27: =IF(C27>0,F27/C27,0) -> 0
A28: 3 | B28: Non-Winter | C28: =C20 -> 246.4224 | F28: =D28+E28 -> 0 | G28: =F28-C28 -> -246.4224 | H28: =IF(C28>0,F28/C28,0) -> 0
A29: 4 | B29: Non-Winter | C29: =C20 -> 246.4224 | F29: =D29+E29 -> 0 | G29: =F29-C29 -> -246.4224 | H29: =IF(C29>0,F29/C29,0) -> 0
A30: 5 | B30: Non-Winter | C30: =C20 -> 246.4224 | F30: =D30+E30 -> 0 | G30: =F30-C30 -> -246.4224 | H30: =IF(C30>0,F30/C30,0) -> 0
A31: 6 | B31: Non-Winter | C31: =C20 -> 246.4224 | F31: =D31+E31 -> 0 | G31: =F31-C31 -> -246.4224 | H31: =IF(C31>0,F31/C31,0) -> 0
A32: 7 | B32: Non-Winter | C32: =C20 -> 246.4224 | F32: =D32+E32 -> 0 | G32: =F32-C32 -> -246.4224 | H32: =IF(C32>0,F32/C32,0) -> 0
A33: 8 | B33: Non-Winter | C33: =C20 -> 246.4224 | F33: =D33+E33 -> 0 | G33: =F33-C33 -> -246.4224 | H33: =IF(C33>0,F33/C33,0) -> 0
A34: 9 | B34: Non-Winter | C34: =C20 -> 246.4224 | F34: =D34+E34 -> 0 | G34: =F34-C34 -> -246.4224 | H34: =IF(C34>0,F34/C34,0) -> 0
A35: 10 | B35: Non-Winter | C35: =C20 -> 246.4224 | F35: =D35+E35 -> 0 | G35: =F35-C35 -> -246.4224 | H35: =IF(C35>0,F35/C35,0) -> 0
A36: 11 | B36: Non-Winter | C36: =C20 -> 246.4224 | F36: =D36+E36 -> 0 | G36: =F36-C36 -> -246.4224 | H36: =IF(C36>0,F36/C36,0) -> 0
A37: 12 | B37: Non-Winter | C37: =C20 -> 246.4224 | F37: =D37+E37 -> 0 | G37: =F37-C37 -> -246.4224 | H37: =IF(C37>0,F37/C37,0) -> 0
A38: 13 | B38: Non-Winter | C38: =C20 -> 246.4224 | F38: =D38+E38 -> 0 | G38: =F38-C38 -> -246.4224 | H38: =IF(C38>0,F38/C38,0) -> 0
A39: TOTAL (Wks 1-13) | C39: =SUM(C26:C38) -> 3203.4912 | D39: =SUM(D26:D38) -> 0 | E39: =SUM(E26:E38) -> 0 | F39: =SUM(F26:F38) -> 0 | G39: =F39-C39 -> -3203.4912 | H39: =IF(C39>0,F39/C39,0) -> 0 | I39: =SUM(I26:I38) -> 0 | J39: =SUM(J26:J38) -> 0
A40: RAG Status | B40: =IF(H39>=1,"GREEN",IF(H39>=0.8,"AMBER","RED")) -> RED
A42: STAFF DEPLOYED AT THIS PRACTICE
A43: Staff Name | B43: Role | C43: Contract Type | D43: Sessions/Wk | E43: Appts/Session | F43: Appts/Wk | G43: Cost/Session (£) | H43: Annual Cost (£) | I43: On-Costs (£) | J43: Total (£)
F44: =IF(D44="","",D44*E44) | H44: =IF(D44="","",D44*G44) | I44: =IF(H44="","",H44*Assumptions!B17) | J44: =IF(H44="","",H44+I44)
F45: =IF(D45="","",D45*E45) | H45: =IF(D45="","",D45*G45) | I45: =IF(H45="","",H45*Assumptions!B17) | J45: =IF(H45="","",H45+I45)
F46: =IF(D46="","",D46*E46) | H46: =IF(D46="","",D46*G46) | I46: =IF(H46="","",H46*Assumptions!B17) | J46: =IF(H46="","",H46+I46)
F47: =IF(D47="","",D47*E47) | H47: =IF(D47="","",D47*G47) | I47: =IF(H47="","",H47*Assumptions!B17) | J47: =IF(H47="","",H47+I47)
F48: =IF(D48="","",D48*E48) | H48: =IF(D48="","",D48*G48) | I48: =IF(H48="","",H48*Assumptions!B17) | J48: =IF(H48="","",H48+I48)
F49: =IF(D49="","",D49*E49) | H49: =IF(D49="","",D49*G49) | I49: =IF(H49="","",H49*Assumptions!B17) | J49: =IF(H49="","",H49+I49)
F50: =IF(D50="","",D50*E50) | H50: =IF(D50="","",D50*G50) | I50: =IF(H50="","",H50*Assumptions!B17) | J50: =IF(H50="","",H50+I50)
F51: =IF(D51="","",D51*E51) | H51: =IF(D51="","",D51*G51) | I51: =IF(H51="","",H51*Assumptions!B17) | J51: =IF(H51="","",H51+I51)
F52: =IF(D52="","",D52*E52) | H52: =IF(D52="","",D52*G52) | I52: =IF(H52="","",H52*Assumptions!B17) | J52: =IF(H52="","",H52+I52)
F53: =IF(D53="","",D53*E53) | H53: =IF(D53="","",D53*G53) | I53: =IF(H53="","",H53*Assumptions!B17) | J53: =IF(H53="","",H53+I53)
A54: TOTAL STAFF COST | D54: =SUM(D44:D53) -> 0 | F54: =SUM(F44:F53) -> 0 | H54: =SUM(H44:H53) -> 0 | I54: =SUM(I44:I53) -> 0 | J54: =SUM(J44:J53) -> 0
A56: BUY-BACK APPLICATIONS FOR THIS PRACTICE
A57: Staff Name | B57: Role | C57: Sessions/Wk | D57: Rate/Session (£) | E57: Annual (£) | F57: On-Costs (£) | G57: Total inc OC (£) | H57: Same-Day % | I57: Claim Value (£) | J57: Status
E58: =IF(C58="","",C58*D58) | F58: =IF(E58="","",E58*Assumptions!B17) | G58: =IF(E58="","",E58+F58) | I58: =IF(G58="","",G58*H58)
E59: =IF(C59="","",C59*D59) | F59: =IF(E59="","",E59*Assumptions!B17) | G59: =IF(E59="","",E59+F59) | I59: =IF(G59="","",G59*H59)
E60: =IF(C60="","",C60*D60) | F60: =IF(E60="","",E60*Assumptions!B17) | G60: =IF(E60="","",E60+F60) | I60: =IF(G60="","",G60*H60)
E61: =IF(C61="","",C61*D61) | F61: =IF(E61="","",E61*Assumptions!B17) | G61: =IF(E61="","",E61+F61) | I61: =IF(G61="","",G61*H61)
E62: =IF(C62="","",C62*D62) | F62: =IF(E62="","",E62*Assumptions!B17) | G62: =IF(E62="","",E62+F62) | I62: =IF(G62="","",G62*H62)
A63: TOTAL BUY-BACK | C63: =SUM(C58:C62) -> 0 | E63: =SUM(E58:E62) -> 0 | F63: =SUM(F58:F62) -> 0 | G63: =SUM(G58:G62) -> 0 | I63: =SUM(I58:I62) -> 0
A65: MONTHLY CASH FLOW — THIS PRACTICE (OPEN BOOK)
A66: Month | B66: Instalment (£) | C66: Cumul. Paid (£) | D66: New SDA Spend (£) | E66: Buy-Back Drawn (£) | F66: Total Claimed (£) | G66: Cumul. Claimed (£) | H66: Headroom (£) | I66: % Drawn | J66: RAG
A67: April | B67: ='Practice Allocations'!E5 -> 35571.83 | C67: =B67*1 -> 35571.83 | F67: =D67+E67 -> 0 | G67: =F67 -> 0 | H67: =C67-G67 -> 35571.83 | I67: =IF(C67>0,G67/C67,0) -> 0 | J67: =IF(H67<0,"OVERSPEND",IF(I67>0.9,"HIGH","OK")) -> OK
A68: May | B68: ='Practice Allocations'!E5 -> 35571.83 | C68: =B68*2 -> 71143.66 | F68: =D68+E68 -> 0 | G68: =G67+F68 -> 0 | H68: =C68-G68 -> 71143.66 | I68: =IF(C68>0,G68/C68,0) -> 0 | J68: =IF(H68<0,"OVERSPEND",IF(I68>0.9,"HIGH","OK")) -> OK
A69: June | B69: ='Practice Allocations'!E5 -> 35571.83 | C69: =B69*3 -> 106715.49 | F69: =D69+E69 -> 0 | G69: =G68+F69 -> 0 | H69: =C69-G69 -> 106715.49 | I69: =IF(C69>0,G69/C69,0) -> 0 | J69: =IF(H69<0,"OVERSPEND",IF(I69>0.9,"HIGH","OK")) -> OK
A70: July | B70: ='Practice Allocations'!E5 -> 35571.83 | C70: =B70*4 -> 142287.32 | F70: =D70+E70 -> 0 | G70: =G69+F70 -> 0 | H70: =C70-G70 -> 142287.32 | I70: =IF(C70>0,G70/C70,0) -> 0 | J70: =IF(H70<0,"OVERSPEND",IF(I70>0.9,"HIGH","OK")) -> OK
A71: August | B71: ='Practice Allocations'!E5 -> 35571.83 | C71: =B71*5 -> 177859.15 | F71: =D71+E71 -> 0 | G71: =G70+F71 -> 0 | H71: =C71-G71 -> 177859.15 | I71: =IF(C71>0,G71/C71,0) -> 0 | J71: =IF(H71<0,"OVERSPEND",IF(I71>0.9,"HIGH","OK")) -> OK
A72: September | B72: ='Practice Allocations'!E5 -> 35571.83 | C72: =B72*6 -> 213430.98 | F72: =D72+E72 -> 0 | G72: =G71+F72 -> 0 | H72: =C72-G72 -> 213430.98 | I72: =IF(C72>0,G72/C72,0) -> 0 | J72: =IF(H72<0,"OVERSPEND",IF(I72>0.9,"HIGH","OK")) -> OK
A73: October | B73: ='Practice Allocations'!E5 -> 35571.83 | C73: =B73*7 -> 249002.81 | F73: =D73+E73 -> 0 | G73: =G72+F73 -> 0 | H73: =C73-G73 -> 249002.81 | I73: =IF(C73>0,G73/C73,0) -> 0 | J73: =IF(H73<0,"OVERSPEND",IF(I73>0.9,"HIGH","OK")) -> OK
A74: November | B74: ='Practice Allocations'!E5 -> 35571.83 | C74: =B74*8 -> 284574.64 | F74: =D74+E74 -> 0 | G74: =G73+F74 -> 0 | H74: =C74-G74 -> 284574.64 | I74: =IF(C74>0,G74/C74,0) -> 0 | J74: =IF(H74<0,"OVERSPEND",IF(I74>0.9,"HIGH","OK")) -> OK
A75: December | B75: ='Practice Allocations'!E5 -> 35571.83 | C75: =B75*9 -> 320146.47 | F75: =D75+E75 -> 0 | G75: =G74+F75 -> 0 | H75: =C75-G75 -> 320146.47 | I75: =IF(C75>0,G75/C75,0) -> 0 | J75: =IF(H75<0,"OVERSPEND",IF(I75>0.9,"HIGH","OK")) -> OK
A76: January | B76: ='Practice Allocations'!E5 -> 35571.83 | C76: =B76*10 -> 355718.3 | F76: =D76+E76 -> 0 | G76: =G75+F76 -> 0 | H76: =C76-G76 -> 355718.3 | I76: =IF(C76>0,G76/C76,0) -> 0 | J76: =IF(H76<0,"OVERSPEND",IF(I76>0.9,"HIGH","OK")) -> OK
A77: February | B77: ='Practice Allocations'!E5 -> 35571.83 | C77: =B77*11 -> 391290.13 | F77: =D77+E77 -> 0 | G77: =G76+F77 -> 0 | H77: =C77-G77 -> 391290.13 | I77: =IF(C77>0,G77/C77,0) -> 0 | J77: =IF(H77<0,"OVERSPEND",IF(I77>0.9,"HIGH","OK")) -> OK
A78: March | B78: ='Practice Allocations'!E5 -> 35571.83 | C78: =B78*12 -> 426861.96 | F78: =D78+E78 -> 0 | G78: =G77+F78 -> 0 | H78: =C78-G78 -> 426861.96 | I78: =IF(C78>0,G78/C78,0) -> 0 | J78: =IF(H78<0,"OVERSPEND",IF(I78>0.9,"HIGH","OK")) -> OK
A79: ANNUAL | B79: =SUM(B67:B78) -> 426861.96 | C79: =C78 -> 426861.96 | D79: =SUM(D67:D78) -> 0 | E79: =SUM(E67:E78) -> 0 | F79: =SUM(F67:F78) -> 0 | G79: =G78 -> 0 | H79: =H78 -> 426861.96 | I79: =I78 -> 0
A81: COMPLIANCE SUMMARY
A82: Annual appointment target | B82: =F22 -> 13446.233
A83: Appointments delivered YTD | B83: =F39 -> 0
A84: % of annual target achieved | B84: =IF(B82>0,B83/B82,0) -> 0
A85: Average weekly delivery (first 13 wks) | B85: =IF(COUNTA(F26:F38)>0,AVERAGE(F26:F38),0) -> 0
A86: Non-winter weekly target | B86: =C20 -> 246.4224
A87: Variance (avg vs target) | B87: =B85-B86 -> -246.4224
A88: Remote % (of total delivered) | B88: =IF(F39>0,E39/F39,0) -> 0
A89: Remote % compliant? (≥50%) | B89: =IF(B90>=0.5,"YES — Compliant","NO — Below 50%") -> NO — Below 50%
A90: Total workforce cost (this practice) | B90: =J54 -> 0
A91: Total buy-back claims | B91: =I63 -> 0
A92: Total expenditure (staff + buy-back) | B92: =B90+B91 -> 0
A93: Budget remaining | B93: ='Practice Allocations'!D5-B94 -> 426861.96
A95: REINVESTMENT TRACKING (BUY-BACK PRACTICES ONLY)
A96: Buy-Back Ref | B96: Reinvestment Plan | C96: New Role Recruited | D96: Salary (£) | E96: Start Date | F96: Status | G96: Evidence
A103: PRACTICE NOTES & ACTIONS
A104: Date | B104: Note / Action | C104: Owner | D104: Status | E104: Due Date

Sheet Springfield
A1: Springfield Surgery — NRES SDA PRACTICE DASHBOARD
A2: Complete view: contract allocation, targets, actuals, workforce, buy-back, cash flow & compliance
A4: PRACTICE PROFILE
A5: Practice Name | B5: =Assumptions!A31 -> Springfield Surgery
A6: List Size | B6: =Assumptions!B31 -> 12611
A7: Hub / Spoke | B7: SPOKE
A8: Clinical System | B8: EMIS
A9: % of Neighbourhood | B9: =Assumptions!E31 -> 0.14077291
A11: CONTRACT ALLOCATION (OPEN BOOK)
A12: Metric | B12: Value
A13: Annual Allocation | B13: ='Practice Allocations'!D6 -> 332047.63
A14: Monthly Instalment (1/12th) | B14: ='Practice Allocations'!E6 -> 27670.636
A15: Recruitment Budget (75%) | B15: ='Practice Allocations'!F6 -> 249035.72
A16: Overheads (25%) | B16: ='Practice Allocations'!D6*Assumptions!B16 -> 83011.908
A18: WEEKLY APPOINTMENT TARGETS
A19: Period | B19: Weeks | C19: Target/Wk | D19: F2F (50%) | E19: Remote (50%) | F19: Seasonal Total
A20: Non-Winter | B20: =Assumptions!B10 -> 39 | C20: ='Practice Allocations'!G6 -> 191.6872 | D20: ='Practice Allocations'!H6 -> 95.8436 | E20: ='Practice Allocations'!I6 -> 95.8436 | F20: =B20*C20 -> 7475.8008
A21: Winter | B21: =Assumptions!B11 -> 13 | C21: ='Practice Allocations'!J6 -> 229.5202 | D21: ='Practice Allocations'!K6 -> 114.7601 | E21: ='Practice Allocations'!L6 -> 114.7601 | F21: =B21*C21 -> 2983.7626
A22: ANNUAL TOTAL | B22: =B20+B21 -> 52 | F22: ='Practice Allocations'!M6 -> 10459.563
A24: WEEKLY ACTUALS vs TARGETS (FIRST 13 WEEKS — ADD MORE AS NEEDED)
A25: Week | B25: Period | C25: Target | D25: F2F Actual | E25: Remote Actual | F25: Total Actual | G25: Variance | H25: % Achieved | I25: New SDA | J25: Buy-Back
A26: 1 | B26: Non-Winter | C26: =C20 -> 191.6872 | F26: =D26+E26 -> 0 | G26: =F26-C26 -> -191.6872 | H26: =IF(C26>0,F26/C26,0) -> 0
A27: 2 | B27: Non-Winter | C27: =C20 -> 191.6872 | F27: =D27+E27 -> 0 | G27: =F27-C27 -> -191.6872 | H27: =IF(C27>0,F27/C27,0) -> 0
A28: 3 | B28: Non-Winter | C28: =C20 -> 191.6872 | F28: =D28+E28 -> 0 | G28: =F28-C28 -> -191.6872 | H28: =IF(C28>0,F28/C28,0) -> 0
A29: 4 | B29: Non-Winter | C29: =C20 -> 191.6872 | F29: =D29+E29 -> 0 | G29: =F29-C29 -> -191.6872 | H29: =IF(C29>0,F29/C29,0) -> 0
A30: 5 | B30: Non-Winter | C30: =C20 -> 191.6872 | F30: =D30+E30 -> 0 | G30: =F30-C30 -> -191.6872 | H30: =IF(C30>0,F30/C30,0) -> 0
A31: 6 | B31: Non-Winter | C31: =C20 -> 191.6872 | F31: =D31+E31 -> 0 | G31: =F31-C31 -> -191.6872 | H31: =IF(C31>0,F31/C31,0) -> 0
A32: 7 | B32: Non-Winter | C32: =C20 -> 191.6872 | F32: =D32+E32 -> 0 | G32: =F32-C32 -> -191.6872 | H32: =IF(C32>0,F32/C32,0) -> 0
A33: 8 | B33: Non-Winter | C33: =C20 -> 191.6872 | F33: =D33+E33 -> 0 | G33: =F33-C33 -> -191.6872 | H33: =IF(C33>0,F33/C33,0) -> 0
A34: 9 | B34: Non-Winter | C34: =C20 -> 191.6872 | F34: =D34+E34 -> 0 | G34: =F34-C34 -> -191.6872 | H34: =IF(C34>0,F34/C34,0) -> 0
A35: 10 | B35: Non-Winter | C35: =C20 -> 191.6872 | F35: =D35+E35 -> 0 | G35: =F35-C35 -> -191.6872 | H35: =IF(C35>0,F35/C35,0) -> 0
A36: 11 | B36: Non-Winter | C36: =C20 -> 191.6872 | F36: =D36+E36 -> 0 | G36: =F36-C36 -> -191.6872 | H36: =IF(C36>0,F36/C36,0) -> 0
A37: 12 | B37: Non-Winter | C37: =C20 -> 191.6872 | F37: =D37+E37 -> 0 | G37: =F37-C37 -> -191.6872 | H37: =IF(C37>0,F37/C37,0) -> 0
A38: 13 | B38: Non-Winter | C38: =C20 -> 191.6872 | F38: =D38+E38 -> 0 | G38: =F38-C38 -> -191.6872 | H38: =IF(C38>0,F38/C38,0) -> 0
A39: TOTAL (Wks 1-13) | C39: =SUM(C26:C38) -> 2491.9336 | D39: =SUM(D26:D38) -> 0 | E39: =SUM(E26:E38) -> 0 | F39: =SUM(F26:F38) -> 0 | G39: =F39-C39 -> -2491.9336 | H39: =IF(C39>0,F39/C39,0) -> 0 | I39: =SUM(I26:I38) -> 0 | J39: =SUM(J26:J38) -> 0
A40: RAG Status | B40: =IF(H39>=1,"GREEN",IF(H39>=0.8,"AMBER","RED")) -> RED
A42: STAFF DEPLOYED AT THIS PRACTICE
A43: Staff Name | B43: Role | C43: Contract Type | D43: Sessions/Wk | E43: Appts/Session | F43: Appts/Wk | G43: Cost/Session (£) | H43: Annual Cost (£) | I43: On-Costs (£) | J43: Total (£)
F44: =IF(D44="","",D44*E44) | H44: =IF(D44="","",D44*G44) | I44: =IF(H44="","",H44*Assumptions!B17) | J44: =IF(H44="","",H44+I44)
F45: =IF(D45="","",D45*E45) | H45: =IF(D45="","",D45*G45) | I45: =IF(H45="","",H45*Assumptions!B17) | J45: =IF(H45="","",H45+I45)
F46: =IF(D46="","",D46*E46) | H46: =IF(D46="","",D46*G46) | I46: =IF(H46="","",H46*Assumptions!B17) | J46: =IF(H46="","",H46+I46)
F47: =IF(D47="","",D47*E47) | H47: =IF(D47="","",D47*G47) | I47: =IF(H47="","",H47*Assumptions!B17) | J47: =IF(H47="","",H47+I47)
F48: =IF(D48="","",D48*E48) | H48: =IF(D48="","",D48*G48) | I48: =IF(H48="","",H48*Assumptions!B17) | J48: =IF(H48="","",H48+I48)
F49: =IF(D49="","",D49*E49) | H49: =IF(D49="","",D49*G49) | I49: =IF(H49="","",H49*Assumptions!B17) | J49: =IF(H49="","",H49+I49)
F50: =IF(D50="","",D50*E50) | H50: =IF(D50="","",D50*G50) | I50: =IF(H50="","",H50*Assumptions!B17) | J50: =IF(H50="","",H50+I50)
F51: =IF(D51="","",D51*E51) | H51: =IF(D51="","",D51*G51) | I51: =IF(H51="","",H51*Assumptions!B17) | J51: =IF(H51="","",H51+I51)
F52: =IF(D52="","",D52*E52) | H52: =IF(D52="","",D52*G52) | I52: =IF(H52="","",H52*Assumptions!B17) | J52: =IF(H52="","",H52+I52)
F53: =IF(D53="","",D53*E53) | H53: =IF(D53="","",D53*G53) | I53: =IF(H53="","",H53*Assumptions!B17) | J53: =IF(H53="","",H53+I53)
A54: TOTAL STAFF COST | D54: =SUM(D44:D53) -> 0 | F54: =SUM(F44:F53) -> 0 | H54: =SUM(H44:H53) -> 0 | I54: =SUM(I44:I53) -> 0 | J54: =SUM(J44:J53) -> 0
A56: BUY-BACK APPLICATIONS FOR THIS PRACTICE
A57: Staff Name | B57: Role | C57: Sessions/Wk | D57: Rate/Session (£) | E57: Annual (£) | F57: On-Costs (£) | G57: Total inc OC (£) | H57: Same-Day % | I57: Claim Value (£) | J57: Status
E58: =IF(C58="","",C58*D58) | F58: =IF(E58="","",E58*Assumptions!B17) | G58: =IF(E58="","",E58+F58) | I58: =IF(G58="","",G58*H58)
E59: =IF(C59="","",C59*D59) | F59: =IF(E59="","",E59*Assumptions!B17) | G59: =IF(E59="","",E59+F59) | I59: =IF(G59="","",G59*H59)
E60: =IF(C60="","",C60*D60) | F60: =IF(E60="","",E60*Assumptions!B17) | G60: =IF(E60="","",E60+F60) | I60: =IF(G60="","",G60*H60)
E61: =IF(C61="","",C61*D61) | F61: =IF(E61="","",E61*Assumptions!B17) | G61: =IF(E61="","",E61+F61) | I61: =IF(G61="","",G61*H61)
E62: =IF(C62="","",C62*D62) | F62: =IF(E62="","",E62*Assumptions!B17) | G62: =IF(E62="","",E62+F62) | I62: =IF(G62="","",G62*H62)
A63: TOTAL BUY-BACK | C63: =SUM(C58:C62) -> 0 | E63: =SUM(E58:E62) -> 0 | F63: =SUM(F58:F62) -> 0 | G63: =SUM(G58:G62) -> 0 | I63: =SUM(I58:I62) -> 0
A65: MONTHLY CASH FLOW — THIS PRACTICE (OPEN BOOK)
A66: Month | B66: Instalment (£) | C66: Cumul. Paid (£) | D66: New SDA Spend (£) | E66: Buy-Back Drawn (£) | F66: Total Claimed (£) | G66: Cumul. Claimed (£) | H66: Headroom (£) | I66: % Drawn | J66: RAG
A67: April | B67: ='Practice Allocations'!E6 -> 27670.636 | C67: =B67*1 -> 27670.636 | F67: =D67+E67 -> 0 | G67: =F67 -> 0 | H67: =C67-G67 -> 27670.636 | I67: =IF(C67>0,G67/C67,0) -> 0 | J67: =IF(H67<0,"OVERSPEND",IF(I67>0.9,"HIGH","OK")) -> OK
A68: May | B68: ='Practice Allocations'!E6 -> 27670.636 | C68: =B68*2 -> 55341.272 | F68: =D68+E68 -> 0 | G68: =G67+F68 -> 0 | H68: =C68-G68 -> 55341.272 | I68: =IF(C68>0,G68/C68,0) -> 0 | J68: =IF(H68<0,"OVERSPEND",IF(I68>0.9,"HIGH","OK")) -> OK
A69: June | B69: ='Practice Allocations'!E6 -> 27670.636 | C69: =B69*3 -> 83011.908 | F69: =D69+E69 -> 0 | G69: =G68+F69 -> 0 | H69: =C69-G69 -> 83011.908 | I69: =IF(C69>0,G69/C69,0) -> 0 | J69: =IF(H69<0,"OVERSPEND",IF(I69>0.9,"HIGH","OK")) -> OK
A70: July | B70: ='Practice Allocations'!E6 -> 27670.636 | C70: =B70*4 -> 110682.54 | F70: =D70+E70 -> 0 | G70: =G69+F70 -> 0 | H70: =C70-G70 -> 110682.54 | I70: =IF(C70>0,G70/C70,0) -> 0 | J70: =IF(H70<0,"OVERSPEND",IF(I70>0.9,"HIGH","OK")) -> OK
A71: August | B71: ='Practice Allocations'!E6 -> 27670.636 | C71: =B71*5 -> 138353.18 | F71: =D71+E71 -> 0 | G71: =G70+F71 -> 0 | H71: =C71-G71 -> 138353.18 | I71: =IF(C71>0,G71/C71,0) -> 0 | J71: =IF(H71<0,"OVERSPEND",IF(I71>0.9,"HIGH","OK")) -> OK
A72: September | B72: ='Practice Allocations'!E6 -> 27670.636 | C72: =B72*6 -> 166023.82 | F72: =D72+E72 -> 0 | G72: =G71+F72 -> 0 | H72: =C72-G72 -> 166023.82 | I72: =IF(C72>0,G72/C72,0) -> 0 | J72: =IF(H72<0,"OVERSPEND",IF(I72>0.9,"HIGH","OK")) -> OK
A73: October | B73: ='Practice Allocations'!E6 -> 27670.636 | C73: =B73*7 -> 193694.45 | F73: =D73+E73 -> 0 | G73: =G72+F73 -> 0 | H73: =C73-G73 -> 193694.45 | I73: =IF(C73>0,G73/C73,0) -> 0 | J73: =IF(H73<0,"OVERSPEND",IF(I73>0.9,"HIGH","OK")) -> OK
A74: November | B74: ='Practice Allocations'!E6 -> 27670.636 | C74: =B74*8 -> 221365.09 | F74: =D74+E74 -> 0 | G74: =G73+F74 -> 0 | H74: =C74-G74 -> 221365.09 | I74: =IF(C74>0,G74/C74,0) -> 0 | J74: =IF(H74<0,"OVERSPEND",IF(I74>0.9,"HIGH","OK")) -> OK
A75: December | B75: ='Practice Allocations'!E6 -> 27670.636 | C75: =B75*9 -> 249035.72 | F75: =D75+E75 -> 0 | G75: =G74+F75 -> 0 | H75: =C75-G75 -> 249035.72 | I75: =IF(C75>0,G75/C75,0) -> 0 | J75: =IF(H75<0,"OVERSPEND",IF(I75>0.9,"HIGH","OK")) -> OK
A76: January | B76: ='Practice Allocations'!E6 -> 27670.636 | C76: =B76*10 -> 276706.36 | F76: =D76+E76 -> 0 | G76: =G75+F76 -> 0 | H76: =C76-G76 -> 276706.36 | I76: =IF(C76>0,G76/C76,0) -> 0 | J76: =IF(H76<0,"OVERSPEND",IF(I76>0.9,"HIGH","OK")) -> OK
A77: February | B77: ='Practice Allocations'!E6 -> 27670.636 | C77: =B77*11 -> 304376.99 | F77: =D77+E77 -> 0 | G77: =G76+F77 -> 0 | H77: =C77-G77 -> 304376.99 | I77: =IF(C77>0,G77/C77,0) -> 0 | J77: =IF(H77<0,"OVERSPEND",IF(I77>0.9,"HIGH","OK")) -> OK
A78: March | B78: ='Practice Allocations'!E6 -> 27670.636 | C78: =B78*12 -> 332047.63 | F78: =D78+E78 -> 0 | G78: =G77+F78 -> 0 | H78: =C78-G78 -> 332047.63 | I78: =IF(C78>0,G78/C78,0) -> 0 | J78: =IF(H78<0,"OVERSPEND",IF(I78>0.9,"HIGH","OK")) -> OK
A79: ANNUAL | B79: =SUM(B67:B78) -> 332047.63 | C79: =C78 -> 332047.63 | D79: =SUM(D67:D78) -> 0 | E79: =SUM(E67:E78) -> 0 | F79: =SUM(F67:F78) -> 0 | G79: =G78 -> 0 | H79: =H78 -> 332047.63 | I79: =I78 -> 0
A81: COMPLIANCE SUMMARY
A82: Annual appointment target | B82: =F22 -> 10459.563
A83: Appointments delivered YTD | B83: =F39 -> 0
A84: % of annual target achieved | B84: =IF(B82>0,B83/B82,0) -> 0
A85: Average weekly delivery (first 13 wks) | B85: =IF(COUNTA(F26:F38)>0,AVERAGE(F26:F38),0) -> 0
A86: Non-winter weekly target | B86: =C20 -> 191.6872
A87: Variance (avg vs target) | B87: =B85-B86 -> -191.6872
A88: Remote % (of total delivered) | B88: =IF(F39>0,E39/F39,0) -> 0
A89: Remote % compliant? (≥50%) | B89: =IF(B90>=0.5,"YES — Compliant","NO — Below 50%") -> NO — Below 50%
A90: Total workforce cost (this practice) | B90: =J54 -> 0
A91: Total buy-back claims | B91: =I63 -> 0
A92: Total expenditure (staff + buy-back) | B92: =B90+B91 -> 0
A93: Budget remaining | B93: ='Practice Allocations'!D6-B94 -> 332047.63
A95: REINVESTMENT TRACKING (BUY-BACK PRACTICES ONLY)
A96: Buy-Back Ref | B96: Reinvestment Plan | C96: New Role Recruited | D96: Salary (£) | E96: Start Date | F96: Status | G96: Evidence
A103: PRACTICE NOTES & ACTIONS
A104: Date | B104: Note / Action | C104: Owner | D104: Status | E104: Due Date

Sheet Towcester
A1: Towcester MC — NRES SDA PRACTICE DASHBOARD
A2: Complete view: contract allocation, targets, actuals, workforce, buy-back, cash flow & compliance
A4: PRACTICE PROFILE
A5: Practice Name | B5: =Assumptions!A32 -> Towcester MC
A6: List Size | B6: =Assumptions!B32 -> 11748
A7: Hub / Spoke | B7: SPOKE
A8: Clinical System | B8: EMIS
A9: % of Neighbourhood | B9: =Assumptions!E32 -> 0.13113949
A11: CONTRACT ALLOCATION (OPEN BOOK)
A12: Metric | B12: Value
A13: Annual Allocation | B13: ='Practice Allocations'!D7 -> 309324.84
A14: Monthly Instalment (1/12th) | B14: ='Practice Allocations'!E7 -> 25777.07
A15: Recruitment Budget (75%) | B15: ='Practice Allocations'!F7 -> 231993.63
A16: Overheads (25%) | B16: ='Practice Allocations'!D7*Assumptions!B16 -> 77331.21
A18: WEEKLY APPOINTMENT TARGETS
A19: Period | B19: Weeks | C19: Target/Wk | D19: F2F (50%) | E19: Remote (50%) | F19: Seasonal Total
A20: Non-Winter | B20: =Assumptions!B10 -> 39 | C20: ='Practice Allocations'!G7 -> 178.5696 | D20: ='Practice Allocations'!H7 -> 89.2848 | E20: ='Practice Allocations'!I7 -> 89.2848 | F20: =B20*C20 -> 6964.2144
A21: Winter | B21: =Assumptions!B11 -> 13 | C21: ='Practice Allocations'!J7 -> 213.8136 | D21: ='Practice Allocations'!K7 -> 106.9068 | E21: ='Practice Allocations'!L7 -> 106.9068 | F21: =B21*C21 -> 2779.5768
A22: ANNUAL TOTAL | B22: =B20+B21 -> 52 | F22: ='Practice Allocations'!M7 -> 9743.7912
A24: WEEKLY ACTUALS vs TARGETS (FIRST 13 WEEKS — ADD MORE AS NEEDED)
A25: Week | B25: Period | C25: Target | D25: F2F Actual | E25: Remote Actual | F25: Total Actual | G25: Variance | H25: % Achieved | I25: New SDA | J25: Buy-Back
A26: 1 | B26: Non-Winter | C26: =C20 -> 178.5696 | F26: =D26+E26 -> 0 | G26: =F26-C26 -> -178.5696 | H26: =IF(C26>0,F26/C26,0) -> 0
A27: 2 | B27: Non-Winter | C27: =C20 -> 178.5696 | F27: =D27+E27 -> 0 | G27: =F27-C27 -> -178.5696 | H27: =IF(C27>0,F27/C27,0) -> 0
A28: 3 | B28: Non-Winter | C28: =C20 -> 178.5696 | F28: =D28+E28 -> 0 | G28: =F28-C28 -> -178.5696 | H28: =IF(C28>0,F28/C28,0) -> 0
A29: 4 | B29: Non-Winter | C29: =C20 -> 178.5696 | F29: =D29+E29 -> 0 | G29: =F29-C29 -> -178.5696 | H29: =IF(C29>0,F29/C29,0) -> 0
A30: 5 | B30: Non-Winter | C30: =C20 -> 178.5696 | F30: =D30+E30 -> 0 | G30: =F30-C30 -> -178.5696 | H30: =IF(C30>0,F30/C30,0) -> 0
A31: 6 | B31: Non-Winter | C31: =C20 -> 178.5696 | F31: =D31+E31 -> 0 | G31: =F31-C31 -> -178.5696 | H31: =IF(C31>0,F31/C31,0) -> 0
A32: 7 | B32: Non-Winter | C32: =C20 -> 178.5696 | F32: =D32+E32 -> 0 | G32: =F32-C32 -> -178.5696 | H32: =IF(C32>0,F32/C32,0) -> 0
A33: 8 | B33: Non-Winter | C33: =C20 -> 178.5696 | F33: =D33+E33 -> 0 | G33: =F33-C33 -> -178.5696 | H33: =IF(C33>0,F33/C33,0) -> 0
A34: 9 | B34: Non-Winter | C34: =C20 -> 178.5696 | F34: =D34+E34 -> 0 | G34: =F34-C34 -> -178.5696 | H34: =IF(C34>0,F34/C34,0) -> 0
A35: 10 | B35: Non-Winter | C35: =C20 -> 178.5696 | F35: =D35+E35 -> 0 | G35: =F35-C35 -> -178.5696 | H35: =IF(C35>0,F35/C35,0) -> 0
A36: 11 | B36: Non-Winter | C36: =C20 -> 178.5696 | F36: =D36+E36 -> 0 | G36: =F36-C36 -> -178.5696 | H36: =IF(C36>0,F36/C36,0) -> 0
A37: 12 | B37: Non-Winter | C37: =C20 -> 178.5696 | F37: =D37+E37 -> 0 | G37: =F37-C37 -> -178.5696 | H37: =IF(C37>0,F37/C37,0) -> 0
A38: 13 | B38: Non-Winter | C38: =C20 -> 178.5696 | F38: =D38+E38 -> 0 | G38: =F38-C38 -> -178.5696 | H38: =IF(C38>0,F38/C38,0) -> 0
A39: TOTAL (Wks 1-13) | C39: =SUM(C26:C38) -> 2321.4048 | D39: =SUM(D26:D38) -> 0 | E39: =SUM(E26:E38) -> 0 | F39: =SUM(F26:F38) -> 0 | G39: =F39-C39 -> -2321.4048 | H39: =IF(C39>0,F39/C39,0) -> 0 | I39: =SUM(I26:I38) -> 0 | J39: =SUM(J26:J38) -> 0
A40: RAG Status | B40: =IF(H39>=1,"GREEN",IF(H39>=0.8,"AMBER","RED")) -> RED
A42: STAFF DEPLOYED AT THIS PRACTICE
A43: Staff Name | B43: Role | C43: Contract Type | D43: Sessions/Wk | E43: Appts/Session | F43: Appts/Wk | G43: Cost/Session (£) | H43: Annual Cost (£) | I43: On-Costs (£) | J43: Total (£)
A44: TBC — New GP Recruit | B44: GP | C44: New SDA | D44: 12 | E44: 12 | F44: =IF(D44="","",D44*E44) -> 144 | G44: 12000 | H44: =IF(D44="","",D44*G44) -> 144000 | I44: =IF(H44="","",H44*Assumptions!B17) -> 42307.2 | J44: =IF(H44="","",H44+I44) -> 186307.2
A45: TBC — New ACP Recruit | B45: ACP | C45: New SDA | D45: 8 | E45: 12 | F45: =IF(D45="","",D45*E45) -> 96 | G45: 4391 | H45: =IF(D45="","",D45*G45) -> 35128 | I45: =IF(H45="","",H45*Assumptions!B17) -> 10320.606 | J45: =IF(H45="","",H45+I45) -> 45448.606
F46: =IF(D46="","",D46*E46) | H46: =IF(D46="","",D46*G46) | I46: =IF(H46="","",H46*Assumptions!B17) | J46: =IF(H46="","",H46+I46)
F47: =IF(D47="","",D47*E47) | H47: =IF(D47="","",D47*G47) | I47: =IF(H47="","",H47*Assumptions!B17) | J47: =IF(H47="","",H47+I47)
F48: =IF(D48="","",D48*E48) | H48: =IF(D48="","",D48*G48) | I48: =IF(H48="","",H48*Assumptions!B17) | J48: =IF(H48="","",H48+I48)
F49: =IF(D49="","",D49*E49) | H49: =IF(D49="","",D49*G49) | I49: =IF(H49="","",H49*Assumptions!B17) | J49: =IF(H49="","",H49+I49)
F50: =IF(D50="","",D50*E50) | H50: =IF(D50="","",D50*G50) | I50: =IF(H50="","",H50*Assumptions!B17) | J50: =IF(H50="","",H50+I50)
F51: =IF(D51="","",D51*E51) | H51: =IF(D51="","",D51*G51) | I51: =IF(H51="","",H51*Assumptions!B17) | J51: =IF(H51="","",H51+I51)
F52: =IF(D52="","",D52*E52) | H52: =IF(D52="","",D52*G52) | I52: =IF(H52="","",H52*Assumptions!B17) | J52: =IF(H52="","",H52+I52)
F53: =IF(D53="","",D53*E53) | H53: =IF(D53="","",D53*G53) | I53: =IF(H53="","",H53*Assumptions!B17) | J53: =IF(H53="","",H53+I53)
A54: TOTAL STAFF COST | D54: =SUM(D44:D53) -> 20 | F54: =SUM(F44:F53) -> 240 | H54: =SUM(H44:H53) -> 179128 | I54: =SUM(I44:I53) -> 52627.806 | J54: =SUM(J44:J53) -> 231755.81
A56: BUY-BACK APPLICATIONS FOR THIS PRACTICE
A57: Staff Name | B57: Role | C57: Sessions/Wk | D57: Rate/Session (£) | E57: Annual (£) | F57: On-Costs (£) | G57: Total inc OC (£) | H57: Same-Day % | I57: Claim Value (£) | J57: Status
E58: =IF(C58="","",C58*D58) | F58: =IF(E58="","",E58*Assumptions!B17) | G58: =IF(E58="","",E58+F58) | I58: =IF(G58="","",G58*H58)
E59: =IF(C59="","",C59*D59) | F59: =IF(E59="","",E59*Assumptions!B17) | G59: =IF(E59="","",E59+F59) | I59: =IF(G59="","",G59*H59)
E60: =IF(C60="","",C60*D60) | F60: =IF(E60="","",E60*Assumptions!B17) | G60: =IF(E60="","",E60+F60) | I60: =IF(G60="","",G60*H60)
E61: =IF(C61="","",C61*D61) | F61: =IF(E61="","",E61*Assumptions!B17) | G61: =IF(E61="","",E61+F61) | I61: =IF(G61="","",G61*H61)
E62: =IF(C62="","",C62*D62) | F62: =IF(E62="","",E62*Assumptions!B17) | G62: =IF(E62="","",E62+F62) | I62: =IF(G62="","",G62*H62)
A63: TOTAL BUY-BACK | C63: =SUM(C58:C62) -> 0 | E63: =SUM(E58:E62) -> 0 | F63: =SUM(F58:F62) -> 0 | G63: =SUM(G58:G62) -> 0 | I63: =SUM(I58:I62) -> 0
A65: MONTHLY CASH FLOW — THIS PRACTICE (OPEN BOOK)
A66: Month | B66: Instalment (£) | C66: Cumul. Paid (£) | D66: New SDA Spend (£) | E66: Buy-Back Drawn (£) | F66: Total Claimed (£) | G66: Cumul. Claimed (£) | H66: Headroom (£) | I66: % Drawn | J66: RAG
A67: April | B67: ='Practice Allocations'!E7 -> 25777.07 | C67: =B67*1 -> 25777.07 | F67: =D67+E67 -> 0 | G67: =F67 -> 0 | H67: =C67-G67 -> 25777.07 | I67: =IF(C67>0,G67/C67,0) -> 0 | J67: =IF(H67<0,"OVERSPEND",IF(I67>0.9,"HIGH","OK")) -> OK
A68: May | B68: ='Practice Allocations'!E7 -> 25777.07 | C68: =B68*2 -> 51554.14 | F68: =D68+E68 -> 0 | G68: =G67+F68 -> 0 | H68: =C68-G68 -> 51554.14 | I68: =IF(C68>0,G68/C68,0) -> 0 | J68: =IF(H68<0,"OVERSPEND",IF(I68>0.9,"HIGH","OK")) -> OK
A69: June | B69: ='Practice Allocations'!E7 -> 25777.07 | C69: =B69*3 -> 77331.21 | F69: =D69+E69 -> 0 | G69: =G68+F69 -> 0 | H69: =C69-G69 -> 77331.21 | I69: =IF(C69>0,G69/C69,0) -> 0 | J69: =IF(H69<0,"OVERSPEND",IF(I69>0.9,"HIGH","OK")) -> OK
A70: July | B70: ='Practice Allocations'!E7 -> 25777.07 | C70: =B70*4 -> 103108.28 | F70: =D70+E70 -> 0 | G70: =G69+F70 -> 0 | H70: =C70-G70 -> 103108.28 | I70: =IF(C70>0,G70/C70,0) -> 0 | J70: =IF(H70<0,"OVERSPEND",IF(I70>0.9,"HIGH","OK")) -> OK
A71: August | B71: ='Practice Allocations'!E7 -> 25777.07 | C71: =B71*5 -> 128885.35 | F71: =D71+E71 -> 0 | G71: =G70+F71 -> 0 | H71: =C71-G71 -> 128885.35 | I71: =IF(C71>0,G71/C71,0) -> 0 | J71: =IF(H71<0,"OVERSPEND",IF(I71>0.9,"HIGH","OK")) -> OK
A72: September | B72: ='Practice Allocations'!E7 -> 25777.07 | C72: =B72*6 -> 154662.42 | F72: =D72+E72 -> 0 | G72: =G71+F72 -> 0 | H72: =C72-G72 -> 154662.42 | I72: =IF(C72>0,G72/C72,0) -> 0 | J72: =IF(H72<0,"OVERSPEND",IF(I72>0.9,"HIGH","OK")) -> OK
A73: October | B73: ='Practice Allocations'!E7 -> 25777.07 | C73: =B73*7 -> 180439.49 | F73: =D73+E73 -> 0 | G73: =G72+F73 -> 0 | H73: =C73-G73 -> 180439.49 | I73: =IF(C73>0,G73/C73,0) -> 0 | J73: =IF(H73<0,"OVERSPEND",IF(I73>0.9,"HIGH","OK")) -> OK
A74: November | B74: ='Practice Allocations'!E7 -> 25777.07 | C74: =B74*8 -> 206216.56 | F74: =D74+E74 -> 0 | G74: =G73+F74 -> 0 | H74: =C74-G74 -> 206216.56 | I74: =IF(C74>0,G74/C74,0) -> 0 | J74: =IF(H74<0,"OVERSPEND",IF(I74>0.9,"HIGH","OK")) -> OK
A75: December | B75: ='Practice Allocations'!E7 -> 25777.07 | C75: =B75*9 -> 231993.63 | F75: =D75+E75 -> 0 | G75: =G74+F75 -> 0 | H75: =C75-G75 -> 231993.63 | I75: =IF(C75>0,G75/C75,0) -> 0 | J75: =IF(H75<0,"OVERSPEND",IF(I75>0.9,"HIGH","OK")) -> OK
A76: January | B76: ='Practice Allocations'!E7 -> 25777.07 | C76: =B76*10 -> 257770.7 | F76: =D76+E76 -> 0 | G76: =G75+F76 -> 0 | H76: =C76-G76 -> 257770.7 | I76: =IF(C76>0,G76/C76,0) -> 0 | J76: =IF(H76<0,"OVERSPEND",IF(I76>0.9,"HIGH","OK")) -> OK
A77: February | B77: ='Practice Allocations'!E7 -> 25777.07 | C77: =B77*11 -> 283547.77 | F77: =D77+E77 -> 0 | G77: =G76+F77 -> 0 | H77: =C77-G77 -> 283547.77 | I77: =IF(C77>0,G77/C77,0) -> 0 | J77: =IF(H77<0,"OVERSPEND",IF(I77>0.9,"HIGH","OK")) -> OK
A78: March | B78: ='Practice Allocations'!E7 -> 25777.07 | C78: =B78*12 -> 309324.84 | F78: =D78+E78 -> 0 | G78: =G77+F78 -> 0 | H78: =C78-G78 -> 309324.84 | I78: =IF(C78>0,G78/C78,0) -> 0 | J78: =IF(H78<0,"OVERSPEND",IF(I78>0.9,"HIGH","OK")) -> OK
A79: ANNUAL | B79: =SUM(B67:B78) -> 309324.84 | C79: =C78 -> 309324.84 | D79: =SUM(D67:D78) -> 0 | E79: =SUM(E67:E78) -> 0 | F79: =SUM(F67:F78) -> 0 | G79: =G78 -> 0 | H79: =H78 -> 309324.84 | I79: =I78 -> 0
A81: COMPLIANCE SUMMARY
A82: Annual appointment target | B82: =F22 -> 9743.7912
A83: Appointments delivered YTD | B83: =F39 -> 0
A84: % of annual target achieved | B84: =IF(B82>0,B83/B82,0) -> 0
A85: Average weekly delivery (first 13 wks) | B85: =IF(COUNTA(F26:F38)>0,AVERAGE(F26:F38),0) -> 0
A86: Non-winter weekly target | B86: =C20 -> 178.5696
A87: Variance (avg vs target) | B87: =B85-B86 -> -178.5696
A88: Remote % (of total delivered) | B88: =IF(F39>0,E39/F39,0) -> 0
A89: Remote % compliant? (≥50%) | B89: =IF(B90>=0.5,"YES — Compliant","NO — Below 50%") -> YES — Compliant
A90: Total workforce cost (this practice) | B90: =J54 -> 231755.81
A91: Total buy-back claims | B91: =I63 -> 0
A92: Total expenditure (staff + buy-back) | B92: =B90+B91 -> 231755.81
A93: Budget remaining | B93: ='Practice Allocations'!D7-B94 -> 309324.84
A95: REINVESTMENT TRACKING (BUY-BACK PRACTICES ONLY)
A96: Buy-Back Ref | B96: Reinvestment Plan | C96: New Role Recruited | D96: Salary (£) | E96: Start Date | F96: Status | G96: Evidence
A103: PRACTICE NOTES & ACTIONS
A104: Date | B104: Note / Action | C104: Owner | D104: Status | E104: Due Date
A105: 28/01/2026 | B105: ✅ LIST SIZE CONFIRMED: 11,748 patients (Jan 2026, approved by all practices with Amanda). Chloe's figure was correct. | C105: Malcolm / Amanda | D105: Complete
A106: 28/01/2026 | B106: 🚨 CRITICAL: Chloe reports current SDA provision at 110/wk (year), 120/wk (winter). Target is 179/wk non-winter, 214/wk winter. TOWCESTER IS CURRENTLY AT 62% OF TARGET. New staff needed to MEET TARGETS FIRST — this is New SDA provision, NOT buy-back. Chloe notes figures exclude triaging/unused/DNA — full data pending. | C106: Malcolm / Amanda | D106: Open
A107: 28/01/2026 | B107: Chloe proposes 12-session GP at £12K + ACP at £28.15/hr (24hrs/wk). Total cost £231,760 — virtually the entire recruitment budget with ~£234 remaining. No headroom for contingency. Maths checks out but budget is razor-thin. | C107: Malcolm / Amanda | D107: Open
A108: 28/01/2026 | B108: Chloe questions whether ACP appointments also need 50% F2F — needs clarification from ICB spec. Also mentions wanting to use financial model rather than appointment model for planning. | C108: Malcolm / Amanda | D108: Open
A109: 28/01/2026 | B109: Chloe mentions 14% overheads + 10% buffer = 24% (vs our 25% assumption). Minor difference. She's using 25% 'to be safe' which aligns with our model. | C109: Info | D109: Complete

Sheet Bugbrooke
A1: Bugbrooke Surgery — NRES SDA PRACTICE DASHBOARD
A2: Complete view: contract allocation, targets, actuals, workforce, buy-back, cash flow & compliance
A4: PRACTICE PROFILE
A5: Practice Name | B5: =Assumptions!A33 -> Bugbrooke Surgery
A6: List Size | B6: =Assumptions!B33 -> 10788
A7: Hub / Spoke | B7: SPOKE
A8: Clinical System | B8: SystmOne
A9: % of Neighbourhood | B9: =Assumptions!E33 -> 0.12042329
A11: CONTRACT ALLOCATION (OPEN BOOK)
A12: Metric | B12: Value
A13: Annual Allocation | B13: ='Practice Allocations'!D8 -> 284048.04
A14: Monthly Instalment (1/12th) | B14: ='Practice Allocations'!E8 -> 23670.67
A15: Recruitment Budget (75%) | B15: ='Practice Allocations'!F8 -> 213036.03
A16: Overheads (25%) | B16: ='Practice Allocations'!D8*Assumptions!B16 -> 71012.01
A18: WEEKLY APPOINTMENT TARGETS
A19: Period | B19: Weeks | C19: Target/Wk | D19: F2F (50%) | E19: Remote (50%) | F19: Seasonal Total
A20: Non-Winter | B20: =Assumptions!B10 -> 39 | C20: ='Practice Allocations'!G8 -> 163.9776 | D20: ='Practice Allocations'!H8 -> 81.9888 | E20: ='Practice Allocations'!I8 -> 81.9888 | F20: =B20*C20 -> 6395.1264
A21: Winter | B21: =Assumptions!B11 -> 13 | C21: ='Practice Allocations'!J8 -> 196.3416 | D21: ='Practice Allocations'!K8 -> 98.1708 | E21: ='Practice Allocations'!L8 -> 98.1708 | F21: =B21*C21 -> 2552.4408
A22: ANNUAL TOTAL | B22: =B20+B21 -> 52 | F22: ='Practice Allocations'!M8 -> 8947.5672
A24: WEEKLY ACTUALS vs TARGETS (FIRST 13 WEEKS — ADD MORE AS NEEDED)
A25: Week | B25: Period | C25: Target | D25: F2F Actual | E25: Remote Actual | F25: Total Actual | G25: Variance | H25: % Achieved | I25: New SDA | J25: Buy-Back
A26: 1 | B26: Non-Winter | C26: =C20 -> 163.9776 | F26: =D26+E26 -> 0 | G26: =F26-C26 -> -163.9776 | H26: =IF(C26>0,F26/C26,0) -> 0
A27: 2 | B27: Non-Winter | C27: =C20 -> 163.9776 | F27: =D27+E27 -> 0 | G27: =F27-C27 -> -163.9776 | H27: =IF(C27>0,F27/C27,0) -> 0
A28: 3 | B28: Non-Winter | C28: =C20 -> 163.9776 | F28: =D28+E28 -> 0 | G28: =F28-C28 -> -163.9776 | H28: =IF(C28>0,F28/C28,0) -> 0
A29: 4 | B29: Non-Winter | C29: =C20 -> 163.9776 | F29: =D29+E29 -> 0 | G29: =F29-C29 -> -163.9776 | H29: =IF(C29>0,F29/C29,0) -> 0
A30: 5 | B30: Non-Winter | C30: =C20 -> 163.9776 | F30: =D30+E30 -> 0 | G30: =F30-C30 -> -163.9776 | H30: =IF(C30>0,F30/C30,0) -> 0
A31: 6 | B31: Non-Winter | C31: =C20 -> 163.9776 | F31: =D31+E31 -> 0 | G31: =F31-C31 -> -163.9776 | H31: =IF(C31>0,F31/C31,0) -> 0
A32: 7 | B32: Non-Winter | C32: =C20 -> 163.9776 | F32: =D32+E32 -> 0 | G32: =F32-C32 -> -163.9776 | H32: =IF(C32>0,F32/C32,0) -> 0
A33: 8 | B33: Non-Winter | C33: =C20 -> 163.9776 | F33: =D33+E33 -> 0 | G33: =F33-C33 -> -163.9776 | H33: =IF(C33>0,F33/C33,0) -> 0
A34: 9 | B34: Non-Winter | C34: =C20 -> 163.9776 | F34: =D34+E34 -> 0 | G34: =F34-C34 -> -163.9776 | H34: =IF(C34>0,F34/C34,0) -> 0
A35: 10 | B35: Non-Winter | C35: =C20 -> 163.9776 | F35: =D35+E35 -> 0 | G35: =F35-C35 -> -163.9776 | H35: =IF(C35>0,F35/C35,0) -> 0
A36: 11 | B36: Non-Winter | C36: =C20 -> 163.9776 | F36: =D36+E36 -> 0 | G36: =F36-C36 -> -163.9776 | H36: =IF(C36>0,F36/C36,0) -> 0
A37: 12 | B37: Non-Winter | C37: =C20 -> 163.9776 | F37: =D37+E37 -> 0 | G37: =F37-C37 -> -163.9776 | H37: =IF(C37>0,F37/C37,0) -> 0
A38: 13 | B38: Non-Winter | C38: =C20 -> 163.9776 | F38: =D38+E38 -> 0 | G38: =F38-C38 -> -163.9776 | H38: =IF(C38>0,F38/C38,0) -> 0
A39: TOTAL (Wks 1-13) | C39: =SUM(C26:C38) -> 2131.7088 | D39: =SUM(D26:D38) -> 0 | E39: =SUM(E26:E38) -> 0 | F39: =SUM(F26:F38) -> 0 | G39: =F39-C39 -> -2131.7088 | H39: =IF(C39>0,F39/C39,0) -> 0 | I39: =SUM(I26:I38) -> 0 | J39: =SUM(J26:J38) -> 0
A40: RAG Status | B40: =IF(H39>=1,"GREEN",IF(H39>=0.8,"AMBER","RED")) -> RED
A42: STAFF DEPLOYED AT THIS PRACTICE
A43: Staff Name | B43: Role | C43: Contract Type | D43: Sessions/Wk | E43: Appts/Session | F43: Appts/Wk | G43: Cost/Session (£) | H43: Annual Cost (£) | I43: On-Costs (£) | J43: Total (£)
F44: =IF(D44="","",D44*E44) | H44: =IF(D44="","",D44*G44) | I44: =IF(H44="","",H44*Assumptions!B17) | J44: =IF(H44="","",H44+I44)
F45: =IF(D45="","",D45*E45) | H45: =IF(D45="","",D45*G45) | I45: =IF(H45="","",H45*Assumptions!B17) | J45: =IF(H45="","",H45+I45)
F46: =IF(D46="","",D46*E46) | H46: =IF(D46="","",D46*G46) | I46: =IF(H46="","",H46*Assumptions!B17) | J46: =IF(H46="","",H46+I46)
F47: =IF(D47="","",D47*E47) | H47: =IF(D47="","",D47*G47) | I47: =IF(H47="","",H47*Assumptions!B17) | J47: =IF(H47="","",H47+I47)
F48: =IF(D48="","",D48*E48) | H48: =IF(D48="","",D48*G48) | I48: =IF(H48="","",H48*Assumptions!B17) | J48: =IF(H48="","",H48+I48)
F49: =IF(D49="","",D49*E49) | H49: =IF(D49="","",D49*G49) | I49: =IF(H49="","",H49*Assumptions!B17) | J49: =IF(H49="","",H49+I49)
F50: =IF(D50="","",D50*E50) | H50: =IF(D50="","",D50*G50) | I50: =IF(H50="","",H50*Assumptions!B17) | J50: =IF(H50="","",H50+I50)
F51: =IF(D51="","",D51*E51) | H51: =IF(D51="","",D51*G51) | I51: =IF(H51="","",H51*Assumptions!B17) | J51: =IF(H51="","",H51+I51)
F52: =IF(D52="","",D52*E52) | H52: =IF(D52="","",D52*G52) | I52: =IF(H52="","",H52*Assumptions!B17) | J52: =IF(H52="","",H52+I52)
F53: =IF(D53="","",D53*E53) | H53: =IF(D53="","",D53*G53) | I53: =IF(H53="","",H53*Assumptions!B17) | J53: =IF(H53="","",H53+I53)
A54: TOTAL STAFF COST | D54: =SUM(D44:D53) -> 0 | F54: =SUM(F44:F53) -> 0 | H54: =SUM(H44:H53) -> 0 | I54: =SUM(I44:I53) -> 0 | J54: =SUM(J44:J53) -> 0
A56: BUY-BACK APPLICATIONS FOR THIS PRACTICE
A57: Staff Name | B57: Role | C57: Sessions/Wk | D57: Rate/Session (£) | E57: Annual (£) | F57: On-Costs (£) | G57: Total inc OC (£) | H57: Same-Day % | I57: Claim Value (£) | J57: Status
E58: =IF(C58="","",C58*D58) | F58: =IF(E58="","",E58*Assumptions!B17) | G58: =IF(E58="","",E58+F58) | I58: =IF(G58="","",G58*H58)
E59: =IF(C59="","",C59*D59) | F59: =IF(E59="","",E59*Assumptions!B17) | G59: =IF(E59="","",E59+F59) | I59: =IF(G59="","",G59*H59)
E60: =IF(C60="","",C60*D60) | F60: =IF(E60="","",E60*Assumptions!B17) | G60: =IF(E60="","",E60+F60) | I60: =IF(G60="","",G60*H60)
E61: =IF(C61="","",C61*D61) | F61: =IF(E61="","",E61*Assumptions!B17) | G61: =IF(E61="","",E61+F61) | I61: =IF(G61="","",G61*H61)
E62: =IF(C62="","",C62*D62) | F62: =IF(E62="","",E62*Assumptions!B17) | G62: =IF(E62="","",E62+F62) | I62: =IF(G62="","",G62*H62)
A63: TOTAL BUY-BACK | C63: =SUM(C58:C62) -> 0 | E63: =SUM(E58:E62) -> 0 | F63: =SUM(F58:F62) -> 0 | G63: =SUM(G58:G62) -> 0 | I63: =SUM(I58:I62) -> 0
A65: MONTHLY CASH FLOW — THIS PRACTICE (OPEN BOOK)
A66: Month | B66: Instalment (£) | C66: Cumul. Paid (£) | D66: New SDA Spend (£) | E66: Buy-Back Drawn (£) | F66: Total Claimed (£) | G66: Cumul. Claimed (£) | H66: Headroom (£) | I66: % Drawn | J66: RAG
A67: April | B67: ='Practice Allocations'!E8 -> 23670.67 | C67: =B67*1 -> 23670.67 | F67: =D67+E67 -> 0 | G67: =F67 -> 0 | H67: =C67-G67 -> 23670.67 | I67: =IF(C67>0,G67/C67,0) -> 0 | J67: =IF(H67<0,"OVERSPEND",IF(I67>0.9,"HIGH","OK")) -> OK
A68: May | B68: ='Practice Allocations'!E8 -> 23670.67 | C68: =B68*2 -> 47341.34 | F68: =D68+E68 -> 0 | G68: =G67+F68 -> 0 | H68: =C68-G68 -> 47341.34 | I68: =IF(C68>0,G68/C68,0) -> 0 | J68: =IF(H68<0,"OVERSPEND",IF(I68>0.9,"HIGH","OK")) -> OK
A69: June | B69: ='Practice Allocations'!E8 -> 23670.67 | C69: =B69*3 -> 71012.01 | F69: =D69+E69 -> 0 | G69: =G68+F69 -> 0 | H69: =C69-G69 -> 71012.01 | I69: =IF(C69>0,G69/C69,0) -> 0 | J69: =IF(H69<0,"OVERSPEND",IF(I69>0.9,"HIGH","OK")) -> OK
A70: July | B70: ='Practice Allocations'!E8 -> 23670.67 | C70: =B70*4 -> 94682.68 | F70: =D70+E70 -> 0 | G70: =G69+F70 -> 0 | H70: =C70-G70 -> 94682.68 | I70: =IF(C70>0,G70/C70,0) -> 0 | J70: =IF(H70<0,"OVERSPEND",IF(I70>0.9,"HIGH","OK")) -> OK
A71: August | B71: ='Practice Allocations'!E8 -> 23670.67 | C71: =B71*5 -> 118353.35 | F71: =D71+E71 -> 0 | G71: =G70+F71 -> 0 | H71: =C71-G71 -> 118353.35 | I71: =IF(C71>0,G71/C71,0) -> 0 | J71: =IF(H71<0,"OVERSPEND",IF(I71>0.9,"HIGH","OK")) -> OK
A72: September | B72: ='Practice Allocations'!E8 -> 23670.67 | C72: =B72*6 -> 142024.02 | F72: =D72+E72 -> 0 | G72: =G71+F72 -> 0 | H72: =C72-G72 -> 142024.02 | I72: =IF(C72>0,G72/C72,0) -> 0 | J72: =IF(H72<0,"OVERSPEND",IF(I72>0.9,"HIGH","OK")) -> OK
A73: October | B73: ='Practice Allocations'!E8 -> 23670.67 | C73: =B73*7 -> 165694.69 | F73: =D73+E73 -> 0 | G73: =G72+F73 -> 0 | H73: =C73-G73 -> 165694.69 | I73: =IF(C73>0,G73/C73,0) -> 0 | J73: =IF(H73<0,"OVERSPEND",IF(I73>0.9,"HIGH","OK")) -> OK
A74: November | B74: ='Practice Allocations'!E8 -> 23670.67 | C74: =B74*8 -> 189365.36 | F74: =D74+E74 -> 0 | G74: =G73+F74 -> 0 | H74: =C74-G74 -> 189365.36 | I74: =IF(C74>0,G74/C74,0) -> 0 | J74: =IF(H74<0,"OVERSPEND",IF(I74>0.9,"HIGH","OK")) -> OK
A75: December | B75: ='Practice Allocations'!E8 -> 23670.67 | C75: =B75*9 -> 213036.03 | F75: =D75+E75 -> 0 | G75: =G74+F75 -> 0 | H75: =C75-G75 -> 213036.03 | I75: =IF(C75>0,G75/C75,0) -> 0 | J75: =IF(H75<0,"OVERSPEND",IF(I75>0.9,"HIGH","OK")) -> OK
A76: January | B76: ='Practice Allocations'!E8 -> 23670.67 | C76: =B76*10 -> 236706.7 | F76: =D76+E76 -> 0 | G76: =G75+F76 -> 0 | H76: =C76-G76 -> 236706.7 | I76: =IF(C76>0,G76/C76,0) -> 0 | J76: =IF(H76<0,"OVERSPEND",IF(I76>0.9,"HIGH","OK")) -> OK
A77: February | B77: ='Practice Allocations'!E8 -> 23670.67 | C77: =B77*11 -> 260377.37 | F77: =D77+E77 -> 0 | G77: =G76+F77 -> 0 | H77: =C77-G77 -> 260377.37 | I77: =IF(C77>0,G77/C77,0) -> 0 | J77: =IF(H77<0,"OVERSPEND",IF(I77>0.9,"HIGH","OK")) -> OK
A78: March | B78: ='Practice Allocations'!E8 -> 23670.67 | C78: =B78*12 -> 284048.04 | F78: =D78+E78 -> 0 | G78: =G77+F78 -> 0 | H78: =C78-G78 -> 284048.04 | I78: =IF(C78>0,G78/C78,0) -> 0 | J78: =IF(H78<0,"OVERSPEND",IF(I78>0.9,"HIGH","OK")) -> OK
A79: ANNUAL | B79: =SUM(B67:B78) -> 284048.04 | C79: =C78 -> 284048.04 | D79: =SUM(D67:D78) -> 0 | E79: =SUM(E67:E78) -> 0 | F79: =SUM(F67:F78) -> 0 | G79: =G78 -> 0 | H79: =H78 -> 284048.04 | I79: =I78 -> 0
A81: COMPLIANCE SUMMARY
A82: Annual appointment target | B82: =F22 -> 8947.5672
A83: Appointments delivered YTD | B83: =F39 -> 0
A84: % of annual target achieved | B84: =IF(B82>0,B83/B82,0) -> 0
A85: Average weekly delivery (first 13 wks) | B85: =IF(COUNTA(F26:F38)>0,AVERAGE(F26:F38),0) -> 0
A86: Non-winter weekly target | B86: =C20 -> 163.9776
A87: Variance (avg vs target) | B87: =B85-B86 -> -163.9776
A88: Remote % (of total delivered) | B88: =IF(F39>0,E39/F39,0) -> 0
A89: Remote % compliant? (≥50%) | B89: =IF(B90>=0.5,"YES — Compliant","NO — Below 50%") -> NO — Below 50%
A90: Total workforce cost (this practice) | B90: =J54 -> 0
A91: Total buy-back claims | B91: =I63 -> 0
A92: Total expenditure (staff + buy-back) | B92: =B90+B91 -> 0
A93: Budget remaining | B93: ='Practice Allocations'!D8-B94 -> 284048.04
A95: REINVESTMENT TRACKING (BUY-BACK PRACTICES ONLY)
A96: Buy-Back Ref | B96: Reinvestment Plan | C96: New Role Recruited | D96: Salary (£) | E96: Start Date | F96: Status | G96: Evidence
A103: PRACTICE NOTES & ACTIONS
A104: Date | B104: Note / Action | C104: Owner | D104: Status | E104: Due Date

Sheet Brook
A1: Brook Health Centre — NRES SDA PRACTICE DASHBOARD
A2: Complete view: contract allocation, targets, actuals, workforce, buy-back, cash flow & compliance
A4: PRACTICE PROFILE
A5: Practice Name | B5: =Assumptions!A34 -> Brook Health Centre
A6: List Size | B6: =Assumptions!B34 -> 9069
A7: Hub / Spoke | B7: SPOKE
A8: Clinical System | B8: SystmOne
A9: % of Neighbourhood | B9: =Assumptions!E34 -> 0.1012346
A11: CONTRACT ALLOCATION (OPEN BOOK)
A12: Metric | B12: Value
A13: Annual Allocation | B13: ='Practice Allocations'!D9 -> 238786.77
A14: Monthly Instalment (1/12th) | B14: ='Practice Allocations'!E9 -> 19898.897
A15: Recruitment Budget (75%) | B15: ='Practice Allocations'!F9 -> 179090.08
A16: Overheads (25%) | B16: ='Practice Allocations'!D9*Assumptions!B16 -> 59696.692
A18: WEEKLY APPOINTMENT TARGETS
A19: Period | B19: Weeks | C19: Target/Wk | D19: F2F (50%) | E19: Remote (50%) | F19: Seasonal Total
A20: Non-Winter | B20: =Assumptions!B10 -> 39 | C20: ='Practice Allocations'!G9 -> 137.8488 | D20: ='Practice Allocations'!H9 -> 68.9244 | E20: ='Practice Allocations'!I9 -> 68.9244 | F20: =B20*C20 -> 5376.1032
A21: Winter | B21: =Assumptions!B11 -> 13 | C21: ='Practice Allocations'!J9 -> 165.0558 | D21: ='Practice Allocations'!K9 -> 82.5279 | E21: ='Practice Allocations'!L9 -> 82.5279 | F21: =B21*C21 -> 2145.7254
A22: ANNUAL TOTAL | B22: =B20+B21 -> 52 | F22: ='Practice Allocations'!M9 -> 7521.8286
A24: WEEKLY ACTUALS vs TARGETS (FIRST 13 WEEKS — ADD MORE AS NEEDED)
A25: Week | B25: Period | C25: Target | D25: F2F Actual | E25: Remote Actual | F25: Total Actual | G25: Variance | H25: % Achieved | I25: New SDA | J25: Buy-Back
A26: 1 | B26: Non-Winter | C26: =C20 -> 137.8488 | F26: =D26+E26 -> 0 | G26: =F26-C26 -> -137.8488 | H26: =IF(C26>0,F26/C26,0) -> 0
A27: 2 | B27: Non-Winter | C27: =C20 -> 137.8488 | F27: =D27+E27 -> 0 | G27: =F27-C27 -> -137.8488 | H27: =IF(C27>0,F27/C27,0) -> 0
A28: 3 | B28: Non-Winter | C28: =C20 -> 137.8488 | F28: =D28+E28 -> 0 | G28: =F28-C28 -> -137.8488 | H28: =IF(C28>0,F28/C28,0) -> 0
A29: 4 | B29: Non-Winter | C29: =C20 -> 137.8488 | F29: =D29+E29 -> 0 | G29: =F29-C29 -> -137.8488 | H29: =IF(C29>0,F29/C29,0) -> 0
A30: 5 | B30: Non-Winter | C30: =C20 -> 137.8488 | F30: =D30+E30 -> 0 | G30: =F30-C30 -> -137.8488 | H30: =IF(C30>0,F30/C30,0) -> 0
A31: 6 | B31: Non-Winter | C31: =C20 -> 137.8488 | F31: =D31+E31 -> 0 | G31: =F31-C31 -> -137.8488 | H31: =IF(C31>0,F31/C31,0) -> 0
A32: 7 | B32: Non-Winter | C32: =C20 -> 137.8488 | F32: =D32+E32 -> 0 | G32: =F32-C32 -> -137.8488 | H32: =IF(C32>0,F32/C32,0) -> 0
A33: 8 | B33: Non-Winter | C33: =C20 -> 137.8488 | F33: =D33+E33 -> 0 | G33: =F33-C33 -> -137.8488 | H33: =IF(C33>0,F33/C33,0) -> 0
A34: 9 | B34: Non-Winter | C34: =C20 -> 137.8488 | F34: =D34+E34 -> 0 | G34: =F34-C34 -> -137.8488 | H34: =IF(C34>0,F34/C34,0) -> 0
A35: 10 | B35: Non-Winter | C35: =C20 -> 137.8488 | F35: =D35+E35 -> 0 | G35: =F35-C35 -> -137.8488 | H35: =IF(C35>0,F35/C35,0) -> 0
A36: 11 | B36: Non-Winter | C36: =C20 -> 137.8488 | F36: =D36+E36 -> 0 | G36: =F36-C36 -> -137.8488 | H36: =IF(C36>0,F36/C36,0) -> 0
A37: 12 | B37: Non-Winter | C37: =C20 -> 137.8488 | F37: =D37+E37 -> 0 | G37: =F37-C37 -> -137.8488 | H37: =IF(C37>0,F37/C37,0) -> 0
A38: 13 | B38: Non-Winter | C38: =C20 -> 137.8488 | F38: =D38+E38 -> 0 | G38: =F38-C38 -> -137.8488 | H38: =IF(C38>0,F38/C38,0) -> 0
A39: TOTAL (Wks 1-13) | C39: =SUM(C26:C38) -> 1792.0344 | D39: =SUM(D26:D38) -> 0 | E39: =SUM(E26:E38) -> 0 | F39: =SUM(F26:F38) -> 0 | G39: =F39-C39 -> -1792.0344 | H39: =IF(C39>0,F39/C39,0) -> 0 | I39: =SUM(I26:I38) -> 0 | J39: =SUM(J26:J38) -> 0
A40: RAG Status | B40: =IF(H39>=1,"GREEN",IF(H39>=0.8,"AMBER","RED")) -> RED
A42: STAFF DEPLOYED AT THIS PRACTICE
A43: Staff Name | B43: Role | C43: Contract Type | D43: Sessions/Wk | E43: Appts/Session | F43: Appts/Wk | G43: Cost/Session (£) | H43: Annual Cost (£) | I43: On-Costs (£) | J43: Total (£)
F44: =IF(D44="","",D44*E44) | H44: =IF(D44="","",D44*G44) | I44: =IF(H44="","",H44*Assumptions!B17) | J44: =IF(H44="","",H44+I44)
F45: =IF(D45="","",D45*E45) | H45: =IF(D45="","",D45*G45) | I45: =IF(H45="","",H45*Assumptions!B17) | J45: =IF(H45="","",H45+I45)
F46: =IF(D46="","",D46*E46) | H46: =IF(D46="","",D46*G46) | I46: =IF(H46="","",H46*Assumptions!B17) | J46: =IF(H46="","",H46+I46)
F47: =IF(D47="","",D47*E47) | H47: =IF(D47="","",D47*G47) | I47: =IF(H47="","",H47*Assumptions!B17) | J47: =IF(H47="","",H47+I47)
F48: =IF(D48="","",D48*E48) | H48: =IF(D48="","",D48*G48) | I48: =IF(H48="","",H48*Assumptions!B17) | J48: =IF(H48="","",H48+I48)
F49: =IF(D49="","",D49*E49) | H49: =IF(D49="","",D49*G49) | I49: =IF(H49="","",H49*Assumptions!B17) | J49: =IF(H49="","",H49+I49)
F50: =IF(D50="","",D50*E50) | H50: =IF(D50="","",D50*G50) | I50: =IF(H50="","",H50*Assumptions!B17) | J50: =IF(H50="","",H50+I50)
F51: =IF(D51="","",D51*E51) | H51: =IF(D51="","",D51*G51) | I51: =IF(H51="","",H51*Assumptions!B17) | J51: =IF(H51="","",H51+I51)
F52: =IF(D52="","",D52*E52) | H52: =IF(D52="","",D52*G52) | I52: =IF(H52="","",H52*Assumptions!B17) | J52: =IF(H52="","",H52+I52)
F53: =IF(D53="","",D53*E53) | H53: =IF(D53="","",D53*G53) | I53: =IF(H53="","",H53*Assumptions!B17) | J53: =IF(H53="","",H53+I53)
A54: TOTAL STAFF COST | D54: =SUM(D44:D53) -> 0 | F54: =SUM(F44:F53) -> 0 | H54: =SUM(H44:H53) -> 0 | I54: =SUM(I44:I53) -> 0 | J54: =SUM(J44:J53) -> 0
A56: BUY-BACK APPLICATIONS FOR THIS PRACTICE
A57: Staff Name | B57: Role | C57: Sessions/Wk | D57: Rate/Session (£) | E57: Annual (£) | F57: On-Costs (£) | G57: Total inc OC (£) | H57: Same-Day % | I57: Claim Value (£) | J57: Status
E58: =IF(C58="","",C58*D58) | F58: =IF(E58="","",E58*Assumptions!B17) | G58: =IF(E58="","",E58+F58) | I58: =IF(G58="","",G58*H58)
E59: =IF(C59="","",C59*D59) | F59: =IF(E59="","",E59*Assumptions!B17) | G59: =IF(E59="","",E59+F59) | I59: =IF(G59="","",G59*H59)
E60: =IF(C60="","",C60*D60) | F60: =IF(E60="","",E60*Assumptions!B17) | G60: =IF(E60="","",E60+F60) | I60: =IF(G60="","",G60*H60)
E61: =IF(C61="","",C61*D61) | F61: =IF(E61="","",E61*Assumptions!B17) | G61: =IF(E61="","",E61+F61) | I61: =IF(G61="","",G61*H61)
E62: =IF(C62="","",C62*D62) | F62: =IF(E62="","",E62*Assumptions!B17) | G62: =IF(E62="","",E62+F62) | I62: =IF(G62="","",G62*H62)
A63: TOTAL BUY-BACK | C63: =SUM(C58:C62) -> 0 | E63: =SUM(E58:E62) -> 0 | F63: =SUM(F58:F62) -> 0 | G63: =SUM(G58:G62) -> 0 | I63: =SUM(I58:I62) -> 0
A65: MONTHLY CASH FLOW — THIS PRACTICE (OPEN BOOK)
A66: Month | B66: Instalment (£) | C66: Cumul. Paid (£) | D66: New SDA Spend (£) | E66: Buy-Back Drawn (£) | F66: Total Claimed (£) | G66: Cumul. Claimed (£) | H66: Headroom (£) | I66: % Drawn | J66: RAG
A67: April | B67: ='Practice Allocations'!E9 -> 19898.897 | C67: =B67*1 -> 19898.897 | F67: =D67+E67 -> 0 | G67: =F67 -> 0 | H67: =C67-G67 -> 19898.897 | I67: =IF(C67>0,G67/C67,0) -> 0 | J67: =IF(H67<0,"OVERSPEND",IF(I67>0.9,"HIGH","OK")) -> OK
A68: May | B68: ='Practice Allocations'!E9 -> 19898.897 | C68: =B68*2 -> 39797.795 | F68: =D68+E68 -> 0 | G68: =G67+F68 -> 0 | H68: =C68-G68 -> 39797.795 | I68: =IF(C68>0,G68/C68,0) -> 0 | J68: =IF(H68<0,"OVERSPEND",IF(I68>0.9,"HIGH","OK")) -> OK
A69: June | B69: ='Practice Allocations'!E9 -> 19898.897 | C69: =B69*3 -> 59696.692 | F69: =D69+E69 -> 0 | G69: =G68+F69 -> 0 | H69: =C69-G69 -> 59696.692 | I69: =IF(C69>0,G69/C69,0) -> 0 | J69: =IF(H69<0,"OVERSPEND",IF(I69>0.9,"HIGH","OK")) -> OK
A70: July | B70: ='Practice Allocations'!E9 -> 19898.897 | C70: =B70*4 -> 79595.59 | F70: =D70+E70 -> 0 | G70: =G69+F70 -> 0 | H70: =C70-G70 -> 79595.59 | I70: =IF(C70>0,G70/C70,0) -> 0 | J70: =IF(H70<0,"OVERSPEND",IF(I70>0.9,"HIGH","OK")) -> OK
A71: August | B71: ='Practice Allocations'!E9 -> 19898.897 | C71: =B71*5 -> 99494.488 | F71: =D71+E71 -> 0 | G71: =G70+F71 -> 0 | H71: =C71-G71 -> 99494.488 | I71: =IF(C71>0,G71/C71,0) -> 0 | J71: =IF(H71<0,"OVERSPEND",IF(I71>0.9,"HIGH","OK")) -> OK
A72: September | B72: ='Practice Allocations'!E9 -> 19898.897 | C72: =B72*6 -> 119393.38 | F72: =D72+E72 -> 0 | G72: =G71+F72 -> 0 | H72: =C72-G72 -> 119393.38 | I72: =IF(C72>0,G72/C72,0) -> 0 | J72: =IF(H72<0,"OVERSPEND",IF(I72>0.9,"HIGH","OK")) -> OK
A73: October | B73: ='Practice Allocations'!E9 -> 19898.897 | C73: =B73*7 -> 139292.28 | F73: =D73+E73 -> 0 | G73: =G72+F73 -> 0 | H73: =C73-G73 -> 139292.28 | I73: =IF(C73>0,G73/C73,0) -> 0 | J73: =IF(H73<0,"OVERSPEND",IF(I73>0.9,"HIGH","OK")) -> OK
A74: November | B74: ='Practice Allocations'!E9 -> 19898.897 | C74: =B74*8 -> 159191.18 | F74: =D74+E74 -> 0 | G74: =G73+F74 -> 0 | H74: =C74-G74 -> 159191.18 | I74: =IF(C74>0,G74/C74,0) -> 0 | J74: =IF(H74<0,"OVERSPEND",IF(I74>0.9,"HIGH","OK")) -> OK
A75: December | B75: ='Practice Allocations'!E9 -> 19898.897 | C75: =B75*9 -> 179090.08 | F75: =D75+E75 -> 0 | G75: =G74+F75 -> 0 | H75: =C75-G75 -> 179090.08 | I75: =IF(C75>0,G75/C75,0) -> 0 | J75: =IF(H75<0,"OVERSPEND",IF(I75>0.9,"HIGH","OK")) -> OK
A76: January | B76: ='Practice Allocations'!E9 -> 19898.897 | C76: =B76*10 -> 198988.98 | F76: =D76+E76 -> 0 | G76: =G75+F76 -> 0 | H76: =C76-G76 -> 198988.98 | I76: =IF(C76>0,G76/C76,0) -> 0 | J76: =IF(H76<0,"OVERSPEND",IF(I76>0.9,"HIGH","OK")) -> OK
A77: February | B77: ='Practice Allocations'!E9 -> 19898.897 | C77: =B77*11 -> 218887.87 | F77: =D77+E77 -> 0 | G77: =G76+F77 -> 0 | H77: =C77-G77 -> 218887.87 | I77: =IF(C77>0,G77/C77,0) -> 0 | J77: =IF(H77<0,"OVERSPEND",IF(I77>0.9,"HIGH","OK")) -> OK
A78: March | B78: ='Practice Allocations'!E9 -> 19898.897 | C78: =B78*12 -> 238786.77 | F78: =D78+E78 -> 0 | G78: =G77+F78 -> 0 | H78: =C78-G78 -> 238786.77 | I78: =IF(C78>0,G78/C78,0) -> 0 | J78: =IF(H78<0,"OVERSPEND",IF(I78>0.9,"HIGH","OK")) -> OK
A79: ANNUAL | B79: =SUM(B67:B78) -> 238786.77 | C79: =C78 -> 238786.77 | D79: =SUM(D67:D78) -> 0 | E79: =SUM(E67:E78) -> 0 | F79: =SUM(F67:F78) -> 0 | G79: =G78 -> 0 | H79: =H78 -> 238786.77 | I79: =I78 -> 0
A81: COMPLIANCE SUMMARY
A82: Annual appointment target | B82: =F22 -> 7521.8286
A83: Appointments delivered YTD | B83: =F39 -> 0
A84: % of annual target achieved | B84: =IF(B82>0,B83/B82,0) -> 0
A85: Average weekly delivery (first 13 wks) | B85: =IF(COUNTA(F26:F38)>0,AVERAGE(F26:F38),0) -> 0
A86: Non-winter weekly target | B86: =C20 -> 137.8488
A87: Variance (avg vs target) | B87: =B85-B86 -> -137.8488
A88: Remote % (of total delivered) | B88: =IF(F39>0,E39/F39,0) -> 0
A89: Remote % compliant? (≥50%) | B89: =IF(B90>=0.5,"YES — Compliant","NO — Below 50%") -> NO — Below 50%
A90: Total workforce cost (this practice) | B90: =J54 -> 0
A91: Total buy-back claims | B91: =I63 -> 0
A92: Total expenditure (staff + buy-back) | B92: =B90+B91 -> 0
A93: Budget remaining | B93: ='Practice Allocations'!D9-B94 -> 238786.77
A95: REINVESTMENT TRACKING (BUY-BACK PRACTICES ONLY)
A96: Buy-Back Ref | B96: Reinvestment Plan | C96: New Role Recruited | D96: Salary (£) | E96: Start Date | F96: Status | G96: Evidence
A103: PRACTICE NOTES & ACTIONS
A104: Date | B104: Note / Action | C104: Owner | D104: Status | E104: Due Date

Sheet Denton
A1: Denton Village Surgery — NRES SDA PRACTICE DASHBOARD
A2: Complete view: contract allocation, targets, actuals, workforce, buy-back, cash flow & compliance
A4: PRACTICE PROFILE
A5: Practice Name | B5: =Assumptions!A35 -> Denton Village Surgery
A6: List Size | B6: =Assumptions!B35 -> 6329
A7: Hub / Spoke | B7: SPOKE
A8: Clinical System | B8: SystmOne
A9: % of Neighbourhood | B9: =Assumptions!E35 -> 0.070648777
A11: CONTRACT ALLOCATION (OPEN BOOK)
A12: Metric | B12: Value
A13: Annual Allocation | B13: ='Practice Allocations'!D10 -> 166642.57
A14: Monthly Instalment (1/12th) | B14: ='Practice Allocations'!E10 -> 13886.881
A15: Recruitment Budget (75%) | B15: ='Practice Allocations'!F10 -> 124981.93
A16: Overheads (25%) | B16: ='Practice Allocations'!D10*Assumptions!B16 -> 41660.643
A18: WEEKLY APPOINTMENT TARGETS
A19: Period | B19: Weeks | C19: Target/Wk | D19: F2F (50%) | E19: Remote (50%) | F19: Seasonal Total
A20: Non-Winter | B20: =Assumptions!B10 -> 39 | C20: ='Practice Allocations'!G10 -> 96.2008 | D20: ='Practice Allocations'!H10 -> 48.1004 | E20: ='Practice Allocations'!I10 -> 48.1004 | F20: =B20*C20 -> 3751.8312
A21: Winter | B21: =Assumptions!B11 -> 13 | C21: ='Practice Allocations'!J10 -> 115.1878 | D21: ='Practice Allocations'!K10 -> 57.5939 | E21: ='Practice Allocations'!L10 -> 57.5939 | F21: =B21*C21 -> 1497.4414
A22: ANNUAL TOTAL | B22: =B20+B21 -> 52 | F22: ='Practice Allocations'!M10 -> 5249.2726
A24: WEEKLY ACTUALS vs TARGETS (FIRST 13 WEEKS — ADD MORE AS NEEDED)
A25: Week | B25: Period | C25: Target | D25: F2F Actual | E25: Remote Actual | F25: Total Actual | G25: Variance | H25: % Achieved | I25: New SDA | J25: Buy-Back
A26: 1 | B26: Non-Winter | C26: =C20 -> 96.2008 | F26: =D26+E26 -> 0 | G26: =F26-C26 -> -96.2008 | H26: =IF(C26>0,F26/C26,0) -> 0
A27: 2 | B27: Non-Winter | C27: =C20 -> 96.2008 | F27: =D27+E27 -> 0 | G27: =F27-C27 -> -96.2008 | H27: =IF(C27>0,F27/C27,0) -> 0
A28: 3 | B28: Non-Winter | C28: =C20 -> 96.2008 | F28: =D28+E28 -> 0 | G28: =F28-C28 -> -96.2008 | H28: =IF(C28>0,F28/C28,0) -> 0
A29: 4 | B29: Non-Winter | C29: =C20 -> 96.2008 | F29: =D29+E29 -> 0 | G29: =F29-C29 -> -96.2008 | H29: =IF(C29>0,F29/C29,0) -> 0
A30: 5 | B30: Non-Winter | C30: =C20 -> 96.2008 | F30: =D30+E30 -> 0 | G30: =F30-C30 -> -96.2008 | H30: =IF(C30>0,F30/C30,0) -> 0
A31: 6 | B31: Non-Winter | C31: =C20 -> 96.2008 | F31: =D31+E31 -> 0 | G31: =F31-C31 -> -96.2008 | H31: =IF(C31>0,F31/C31,0) -> 0
A32: 7 | B32: Non-Winter | C32: =C20 -> 96.2008 | F32: =D32+E32 -> 0 | G32: =F32-C32 -> -96.2008 | H32: =IF(C32>0,F32/C32,0) -> 0
A33: 8 | B33: Non-Winter | C33: =C20 -> 96.2008 | F33: =D33+E33 -> 0 | G33: =F33-C33 -> -96.2008 | H33: =IF(C33>0,F33/C33,0) -> 0
A34: 9 | B34: Non-Winter | C34: =C20 -> 96.2008 | F34: =D34+E34 -> 0 | G34: =F34-C34 -> -96.2008 | H34: =IF(C34>0,F34/C34,0) -> 0
A35: 10 | B35: Non-Winter | C35: =C20 -> 96.2008 | F35: =D35+E35 -> 0 | G35: =F35-C35 -> -96.2008 | H35: =IF(C35>0,F35/C35,0) -> 0
A36: 11 | B36: Non-Winter | C36: =C20 -> 96.2008 | F36: =D36+E36 -> 0 | G36: =F36-C36 -> -96.2008 | H36: =IF(C36>0,F36/C36,0) -> 0
A37: 12 | B37: Non-Winter | C37: =C20 -> 96.2008 | F37: =D37+E37 -> 0 | G37: =F37-C37 -> -96.2008 | H37: =IF(C37>0,F37/C37,0) -> 0
A38: 13 | B38: Non-Winter | C38: =C20 -> 96.2008 | F38: =D38+E38 -> 0 | G38: =F38-C38 -> -96.2008 | H38: =IF(C38>0,F38/C38,0) -> 0
A39: TOTAL (Wks 1-13) | C39: =SUM(C26:C38) -> 1250.6104 | D39: =SUM(D26:D38) -> 0 | E39: =SUM(E26:E38) -> 0 | F39: =SUM(F26:F38) -> 0 | G39: =F39-C39 -> -1250.6104 | H39: =IF(C39>0,F39/C39,0) -> 0 | I39: =SUM(I26:I38) -> 0 | J39: =SUM(J26:J38) -> 0
A40: RAG Status | B40: =IF(H39>=1,"GREEN",IF(H39>=0.8,"AMBER","RED")) -> RED
A42: STAFF DEPLOYED AT THIS PRACTICE
A43: Staff Name | B43: Role | C43: Contract Type | D43: Sessions/Wk | E43: Appts/Session | F43: Appts/Wk | G43: Cost/Session (£) | H43: Annual Cost (£) | I43: On-Costs (£) | J43: Total (£)
A44: TBC — New GP Recruit | B44: GP | C44: New SDA | D44: 8 | E44: 12 | F44: =IF(D44="","",D44*E44) -> 96 | G44: 11000 | H44: =IF(D44="","",D44*G44) -> 88000 | I44: =IF(H44="","",H44*Assumptions!B17) -> 25854.4 | J44: =IF(H44="","",H44+I44) -> 113854.4
F45: =IF(D45="","",D45*E45) | H45: =IF(D45="","",D45*G45) | I45: =IF(H45="","",H45*Assumptions!B17) | J45: =IF(H45="","",H45+I45)
F46: =IF(D46="","",D46*E46) | H46: =IF(D46="","",D46*G46) | I46: =IF(H46="","",H46*Assumptions!B17) | J46: =IF(H46="","",H46+I46)
F47: =IF(D47="","",D47*E47) | H47: =IF(D47="","",D47*G47) | I47: =IF(H47="","",H47*Assumptions!B17) | J47: =IF(H47="","",H47+I47)
F48: =IF(D48="","",D48*E48) | H48: =IF(D48="","",D48*G48) | I48: =IF(H48="","",H48*Assumptions!B17) | J48: =IF(H48="","",H48+I48)
F49: =IF(D49="","",D49*E49) | H49: =IF(D49="","",D49*G49) | I49: =IF(H49="","",H49*Assumptions!B17) | J49: =IF(H49="","",H49+I49)
F50: =IF(D50="","",D50*E50) | H50: =IF(D50="","",D50*G50) | I50: =IF(H50="","",H50*Assumptions!B17) | J50: =IF(H50="","",H50+I50)
F51: =IF(D51="","",D51*E51) | H51: =IF(D51="","",D51*G51) | I51: =IF(H51="","",H51*Assumptions!B17) | J51: =IF(H51="","",H51+I51)
F52: =IF(D52="","",D52*E52) | H52: =IF(D52="","",D52*G52) | I52: =IF(H52="","",H52*Assumptions!B17) | J52: =IF(H52="","",H52+I52)
F53: =IF(D53="","",D53*E53) | H53: =IF(D53="","",D53*G53) | I53: =IF(H53="","",H53*Assumptions!B17) | J53: =IF(H53="","",H53+I53)
A54: TOTAL STAFF COST | D54: =SUM(D44:D53) -> 8 | F54: =SUM(F44:F53) -> 96 | H54: =SUM(H44:H53) -> 88000 | I54: =SUM(I44:I53) -> 25854.4 | J54: =SUM(J44:J53) -> 113854.4
A56: BUY-BACK APPLICATIONS FOR THIS PRACTICE
A57: Staff Name | B57: Role | C57: Sessions/Wk | D57: Rate/Session (£) | E57: Annual (£) | F57: On-Costs (£) | G57: Total inc OC (£) | H57: Same-Day % | I57: Claim Value (£) | J57: Status
A58: Existing GP Capacity (Buy-Back) | B58: GP | D58: 11000 | E58: =IF(C58="","",C58*D58) | F58: =IF(E58="","",E58*Assumptions!B17) | G58: =IF(E58="","",E58+F58) | H58: 1 | I58: =IF(G58="","",G58*H58) | J58: Draft
E59: =IF(C59="","",C59*D59) | F59: =IF(E59="","",E59*Assumptions!B17) | G59: =IF(E59="","",E59+F59) | I59: =IF(G59="","",G59*H59)
E60: =IF(C60="","",C60*D60) | F60: =IF(E60="","",E60*Assumptions!B17) | G60: =IF(E60="","",E60+F60) | I60: =IF(G60="","",G60*H60)
E61: =IF(C61="","",C61*D61) | F61: =IF(E61="","",E61*Assumptions!B17) | G61: =IF(E61="","",E61+F61) | I61: =IF(G61="","",G61*H61)
E62: =IF(C62="","",C62*D62) | F62: =IF(E62="","",E62*Assumptions!B17) | G62: =IF(E62="","",E62+F62) | I62: =IF(G62="","",G62*H62)
A63: TOTAL BUY-BACK | C63: =SUM(C58:C62) -> 0 | E63: =SUM(E58:E62) -> 0 | F63: =SUM(F58:F62) -> 0 | G63: =SUM(G58:G62) -> 0 | I63: =SUM(I58:I62) -> 0
A65: MONTHLY CASH FLOW — THIS PRACTICE (OPEN BOOK)
A66: Month | B66: Instalment (£) | C66: Cumul. Paid (£) | D66: New SDA Spend (£) | E66: Buy-Back Drawn (£) | F66: Total Claimed (£) | G66: Cumul. Claimed (£) | H66: Headroom (£) | I66: % Drawn | J66: RAG
A67: April | B67: ='Practice Allocations'!E10 -> 13886.881 | C67: =B67*1 -> 13886.881 | F67: =D67+E67 -> 0 | G67: =F67 -> 0 | H67: =C67-G67 -> 13886.881 | I67: =IF(C67>0,G67/C67,0) -> 0 | J67: =IF(H67<0,"OVERSPEND",IF(I67>0.9,"HIGH","OK")) -> OK
A68: May | B68: ='Practice Allocations'!E10 -> 13886.881 | C68: =B68*2 -> 27773.762 | F68: =D68+E68 -> 0 | G68: =G67+F68 -> 0 | H68: =C68-G68 -> 27773.762 | I68: =IF(C68>0,G68/C68,0) -> 0 | J68: =IF(H68<0,"OVERSPEND",IF(I68>0.9,"HIGH","OK")) -> OK
A69: June | B69: ='Practice Allocations'!E10 -> 13886.881 | C69: =B69*3 -> 41660.643 | F69: =D69+E69 -> 0 | G69: =G68+F69 -> 0 | H69: =C69-G69 -> 41660.643 | I69: =IF(C69>0,G69/C69,0) -> 0 | J69: =IF(H69<0,"OVERSPEND",IF(I69>0.9,"HIGH","OK")) -> OK
A70: July | B70: ='Practice Allocations'!E10 -> 13886.881 | C70: =B70*4 -> 55547.523 | F70: =D70+E70 -> 0 | G70: =G69+F70 -> 0 | H70: =C70-G70 -> 55547.523 | I70: =IF(C70>0,G70/C70,0) -> 0 | J70: =IF(H70<0,"OVERSPEND",IF(I70>0.9,"HIGH","OK")) -> OK
A71: August | B71: ='Practice Allocations'!E10 -> 13886.881 | C71: =B71*5 -> 69434.404 | F71: =D71+E71 -> 0 | G71: =G70+F71 -> 0 | H71: =C71-G71 -> 69434.404 | I71: =IF(C71>0,G71/C71,0) -> 0 | J71: =IF(H71<0,"OVERSPEND",IF(I71>0.9,"HIGH","OK")) -> OK
A72: September | B72: ='Practice Allocations'!E10 -> 13886.881 | C72: =B72*6 -> 83321.285 | F72: =D72+E72 -> 0 | G72: =G71+F72 -> 0 | H72: =C72-G72 -> 83321.285 | I72: =IF(C72>0,G72/C72,0) -> 0 | J72: =IF(H72<0,"OVERSPEND",IF(I72>0.9,"HIGH","OK")) -> OK
A73: October | B73: ='Practice Allocations'!E10 -> 13886.881 | C73: =B73*7 -> 97208.166 | F73: =D73+E73 -> 0 | G73: =G72+F73 -> 0 | H73: =C73-G73 -> 97208.166 | I73: =IF(C73>0,G73/C73,0) -> 0 | J73: =IF(H73<0,"OVERSPEND",IF(I73>0.9,"HIGH","OK")) -> OK
A74: November | B74: ='Practice Allocations'!E10 -> 13886.881 | C74: =B74*8 -> 111095.05 | F74: =D74+E74 -> 0 | G74: =G73+F74 -> 0 | H74: =C74-G74 -> 111095.05 | I74: =IF(C74>0,G74/C74,0) -> 0 | J74: =IF(H74<0,"OVERSPEND",IF(I74>0.9,"HIGH","OK")) -> OK
A75: December | B75: ='Practice Allocations'!E10 -> 13886.881 | C75: =B75*9 -> 124981.93 | F75: =D75+E75 -> 0 | G75: =G74+F75 -> 0 | H75: =C75-G75 -> 124981.93 | I75: =IF(C75>0,G75/C75,0) -> 0 | J75: =IF(H75<0,"OVERSPEND",IF(I75>0.9,"HIGH","OK")) -> OK
A76: January | B76: ='Practice Allocations'!E10 -> 13886.881 | C76: =B76*10 -> 138868.81 | F76: =D76+E76 -> 0 | G76: =G75+F76 -> 0 | H76: =C76-G76 -> 138868.81 | I76: =IF(C76>0,G76/C76,0) -> 0 | J76: =IF(H76<0,"OVERSPEND",IF(I76>0.9,"HIGH","OK")) -> OK
A77: February | B77: ='Practice Allocations'!E10 -> 13886.881 | C77: =B77*11 -> 152755.69 | F77: =D77+E77 -> 0 | G77: =G76+F77 -> 0 | H77: =C77-G77 -> 152755.69 | I77: =IF(C77>0,G77/C77,0) -> 0 | J77: =IF(H77<0,"OVERSPEND",IF(I77>0.9,"HIGH","OK")) -> OK
A78: March | B78: ='Practice Allocations'!E10 -> 13886.881 | C78: =B78*12 -> 166642.57 | F78: =D78+E78 -> 0 | G78: =G77+F78 -> 0 | H78: =C78-G78 -> 166642.57 | I78: =IF(C78>0,G78/C78,0) -> 0 | J78: =IF(H78<0,"OVERSPEND",IF(I78>0.9,"HIGH","OK")) -> OK
A79: ANNUAL | B79: =SUM(B67:B78) -> 166642.57 | C79: =C78 -> 166642.57 | D79: =SUM(D67:D78) -> 0 | E79: =SUM(E67:E78) -> 0 | F79: =SUM(F67:F78) -> 0 | G79: =G78 -> 0 | H79: =H78 -> 166642.57 | I79: =I78 -> 0
A81: COMPLIANCE SUMMARY
A82: Annual appointment target | B82: =F22 -> 5249.2726
A83: Appointments delivered YTD | B83: =F39 -> 0
A84: % of annual target achieved | B84: =IF(B82>0,B83/B82,0) -> 0
A85: Average weekly delivery (first 13 wks) | B85: =IF(COUNTA(F26:F38)>0,AVERAGE(F26:F38),0) -> 0
A86: Non-winter weekly target | B86: =C20 -> 96.2008
A87: Variance (avg vs target) | B87: =B85-B86 -> -96.2008
A88: Remote % (of total delivered) | B88: =IF(F39>0,E39/F39,0) -> 0
A89: Remote % compliant? (≥50%) | B89: =IF(B90>=0.5,"YES — Compliant","NO — Below 50%") -> YES — Compliant
A90: Total workforce cost (this practice) | B90: =J54 -> 113854.4
A91: Total buy-back claims | B91: =I63 -> 0
A92: Total expenditure (staff + buy-back) | B92: =B90+B91 -> 113854.4
A93: Budget remaining | B93: ='Practice Allocations'!D10-B94 -> 166642.57
A95: REINVESTMENT TRACKING (BUY-BACK PRACTICES ONLY)
A96: Buy-Back Ref | B96: Reinvestment Plan | C96: New Role Recruited | D96: Salary (£) | E96: Start Date | F96: Status | G96: Evidence
A97: BB-001 (pending) | B97: Recruit 8-session GP at £11K-£12K DOE for proactive care (Part B) | C97: GP — 8 sessions | F97: Planned
A103: PRACTICE NOTES & ACTIONS
A104: Date | B104: Note / Action | C104: Owner | D104: Status | E104: Due Date
A105: 28/01/2026 | B105: Nicola confirms current SDA provision: 204 GP appts/wk (no leave), 165 when GP on leave, 303 total with ANPs/Paramedic. Target is ~96/wk. STRONG buy-back case — delivering 2-3x minimum. Proposes 8-session GP at £11K-£12K DOE to free existing SDA for Part B. | C105: Nicola Draper | D105: In Progress
A106: 28/01/2026 | B106: Room availability: 5 sessions currently available, can create 3 more with planned changes = 8 total. Can offer 50% remote if needed. | C106: Nicola Draper | D106: Open
A107: 28/01/2026 | B107: Buy-back proposal needs to go through Malcolm & Amanda for equity check. Once approved as part of ICB Buy Back scheme, will do appointment modelling for Part B. | C107: Malcolm / Amanda | D107: Open

Sheet DNA Tracking
A1: DNA (DID NOT ATTEND) TRACKING — WEEKLY BY PRACTICE
A2: Enter weekly DNA counts per practice. DNA rate auto-calculates. Amber ≥5%, Red ≥10%. Feeds into compliance reporting.
A3: Week | B3: Period | C3: Parks DNAs | D3: Brackley DNAs | E3: Springfield DNAs | F3: Towcester DNAs | G3: Bugbrooke DNAs | H3: Brook DNAs | I3: Denton DNAs | J3: Total DNAs | K3: Total Offered | L3: DNA Rate
A4: 1 | B4: Winter | J4: =SUM(C4:I4) -> 0 | K4: ='Compliance Tracker'!J4 -> 0 | L4: =IF(K4>0,J4/K4,0) -> 0
A5: 2 | B5: Winter | J5: =SUM(C5:I5) -> 0 | K5: ='Compliance Tracker'!J5 -> 0 | L5: =IF(K5>0,J5/K5,0) -> 0
A6: 3 | B6: Winter | J6: =SUM(C6:I6) -> 0 | K6: ='Compliance Tracker'!J6 -> 0 | L6: =IF(K6>0,J6/K6,0) -> 0
A7: 4 | B7: Winter | J7: =SUM(C7:I7) -> 0 | K7: ='Compliance Tracker'!J7 -> 0 | L7: =IF(K7>0,J7/K7,0) -> 0
A8: 5 | B8: Winter | J8: =SUM(C8:I8) -> 0 | K8: ='Compliance Tracker'!J8 -> 0 | L8: =IF(K8>0,J8/K8,0) -> 0
A9: 6 | B9: Winter | J9: =SUM(C9:I9) -> 0 | K9: ='Compliance Tracker'!J9 -> 0 | L9: =IF(K9>0,J9/K9,0) -> 0
A10: 7 | B10: Winter | J10: =SUM(C10:I10) -> 0 | K10: ='Compliance Tracker'!J10 -> 0 | L10: =IF(K10>0,J10/K10,0) -> 0
A11: 8 | B11: Winter | J11: =SUM(C11:I11) -> 0 | K11: ='Compliance Tracker'!J11 -> 0 | L11: =IF(K11>0,J11/K11,0) -> 0
A12: 9 | B12: Winter | J12: =SUM(C12:I12) -> 0 | K12: ='Compliance Tracker'!J12 -> 0 | L12: =IF(K12>0,J12/K12,0) -> 0
A13: 10 | B13: Winter | J13: =SUM(C13:I13) -> 0 | K13: ='Compliance Tracker'!J13 -> 0 | L13: =IF(K13>0,J13/K13,0) -> 0
A14: 11 | B14: Winter | J14: =SUM(C14:I14) -> 0 | K14: ='Compliance Tracker'!J14 -> 0 | L14: =IF(K14>0,J14/K14,0) -> 0
A15: 12 | B15: Winter | J15: =SUM(C15:I15) -> 0 | K15: ='Compliance Tracker'!J15 -> 0 | L15: =IF(K15>0,J15/K15,0) -> 0
... A55: 52 | B55: Winter | J55: =SUM(C55:I55) -> 0 | K55: ='Compliance Tracker'!J55 -> 0 | L55: =IF(K55>0,J55/K55,0) -> 0
A58: DNA SUMMARY BY PRACTICE (CUMULATIVE YTD)
A59: Practice | B59: Total DNAs | C59: Avg DNAs/Wk | D59: Est Wasted Cost (£)
A60: The Parks MC | B60: =SUM(C4:C55) -> 0 | C60: =IF(COUNTA(C4:C55)>0,AVERAGE(C4:C55),0) -> 0 | D60: =B60*30 -> 0
A61: Brackley MC | B61: =SUM(D4:D55) -> 0 | C61: =IF(COUNTA(D4:D55)>0,AVERAGE(D4:D55),0) -> 0 | D61: =B61*30 -> 0
A62: Springfield Surgery | B62: =SUM(E4:E55) -> 0 | C62: =IF(COUNTA(E4:E55)>0,AVERAGE(E4:E55),0) -> 0 | D62: =B62*30 -> 0
A63: Towcester MC | B63: =SUM(F4:F55) -> 0 | C63: =IF(COUNTA(F4:F55)>0,AVERAGE(F4:F55),0) -> 0 | D63: =B63*30 -> 0
A64: Bugbrooke Surgery | B64: =SUM(G4:G55) -> 0 | C64: =IF(COUNTA(G4:G55)>0,AVERAGE(G4:G55),0) -> 0 | D64: =B64*30 -> 0
A65: Brook Health Centre | B65: =SUM(H4:H55) -> 0 | C65: =IF(COUNTA(H4:H55)>0,AVERAGE(H4:H55),0) -> 0 | D65: =B65*30 -> 0
A66: Denton Village Surgery | B66: =SUM(I4:I55) -> 0 | C66: =IF(COUNTA(I4:I55)>0,AVERAGE(I4:I55),0) -> 0 | D66: =B66*30 -> 0
A67: NEIGHBOURHOOD TOTAL | B67: =SUM(B60:B66) -> 0 | C67: =IF(COUNTA(J4:J55)>0,AVERAGE(J4:J55),0) -> 0 | D67: =SUM(D60:D66) -> 0
A69: DNA RATE THRESHOLDS (CONFIGURABLE)
A70: Amber threshold | B70: 0.05 | C70: Flag practices above this rate
A71: Red threshold | B71: 0.1 | C71: Escalation required
A72: Est cost per DNA (£) | B72: 30 | C72: Used for wasted cost calculation

Sheet Absence Tracker
A1: ABSENCE TRACKER — ANNUAL LEAVE / SICKNESS / PLT / STUDY LEAVE
A2: Record all staff absences. Sessions lost deduct from expected capacity. Feeds into compliance and trend reporting.
A4: ABSENCE LOG
A5: Date | B5: Staff Name | C5: Practice | D5: Staff Type | E5: Session (AM/PM/Eve) | F5: Absence Type | G5: Appts Lost | H5: Cover Arranged? | I5: Cover By | J5: Notes
A108: ABSENCE SUMMARY BY TYPE
A109: Absence Type | B109: Count | C109: Sessions Lost | D109: Appts Lost | E109: % of Total
A110: Annual Leave | B110: =COUNTIF(F6:F105,"Annual Leave") -> 0 | C110: =B110 -> 0 | D110: =SUMIF(F6:F105,"Annual Leave",G6:G105) -> 0 | E110: =IF(B115>0,B110/B115,0) -> 0
A111: Sickness | B111: =COUNTIF(F6:F105,"Sickness") -> 0 | C111: =B111 -> 0 | D111: =SUMIF(F6:F105,"Sickness",G6:G105) -> 0 | E111: =IF(B115>0,B111/B115,0) -> 0
A112: PLT | B112: =COUNTIF(F6:F105,"PLT") -> 0 | C112: =B112 -> 0 | D112: =SUMIF(F6:F105,"PLT",G6:G105) -> 0 | E112: =IF(B115>0,B112/B115,0) -> 0
A113: Study Leave | B113: =COUNTIF(F6:F105,"Study Leave") -> 0 | C113: =B113 -> 0 | D113: =SUMIF(F6:F105,"Study Leave",G6:G105) -> 0 | E113: =IF(B115>0,B113/B115,0) -> 0
A114: Other | B114: =COUNTIF(F6:F105,"Other") -> 0 | C114: =B114 -> 0 | D114: =SUMIF(F6:F105,"Other",G6:G105) -> 0 | E114: =IF(B115>0,B114/B115,0) -> 0
A115: TOTAL | B115: =SUM(B110:B114) -> 0 | C115: =SUM(C110:C114) -> 0 | D115: =SUM(D110:D114) -> 0
A118: ABSENCE SUMMARY BY PRACTICE
A119: Practice | B119: Total Absences | C119: Appts Lost | D119: Annual Leave | E119: Sickness | F119: PLT | G119: Study Leave | H119: Other
A120: The Parks MC | B120: =COUNTIF(C6:C105,A120) -> 0 | C120: =SUMIF(C6:C105,A120,G6:G105) -> 0 | D120: =COUNTIFS(C6:C105,A120,F6:F105,"Annual Leave") -> 0 | E120: =COUNTIFS(C6:C105,A120,F6:F105,"Sickness") -> 0 | F120: =COUNTIFS(C6:C105,A120,F6:F105,"PLT") -> 0 | G120: =COUNTIFS(C6:C105,A120,F6:F105,"Study Leave") -> 0 | H120: =COUNTIFS(C6:C105,A120,F6:F105,"Other") -> 0
A121: Brackley MC | B121: =COUNTIF(C6:C105,A121) -> 0 | C121: =SUMIF(C6:C105,A121,G6:G105) -> 0 | D121: =COUNTIFS(C6:C105,A121,F6:F105,"Annual Leave") -> 0 | E121: =COUNTIFS(C6:C105,A121,F6:F105,"Sickness") -> 0 | F121: =COUNTIFS(C6:C105,A121,F6:F105,"PLT") -> 0 | G121: =COUNTIFS(C6:C105,A121,F6:F105,"Study Leave") -> 0 | H121: =COUNTIFS(C6:C105,A121,F6:F105,"Other") -> 0
A122: Springfield Surgery | B122: =COUNTIF(C6:C105,A122) -> 0 | C122: =SUMIF(C6:C105,A122,G6:G105) -> 0 | D122: =COUNTIFS(C6:C105,A122,F6:F105,"Annual Leave") -> 0 | E122: =COUNTIFS(C6:C105,A122,F6:F105,"Sickness") -> 0 | F122: =COUNTIFS(C6:C105,A122,F6:F105,"PLT") -> 0 | G122: =COUNTIFS(C6:C105,A122,F6:F105,"Study Leave") -> 0 | H122: =COUNTIFS(C6:C105,A122,F6:F105,"Other") -> 0
A123: Towcester MC | B123: =COUNTIF(C6:C105,A123) -> 0 | C123: =SUMIF(C6:C105,A123,G6:G105) -> 0 | D123: =COUNTIFS(C6:C105,A123,F6:F105,"Annual Leave") -> 0 | E123: =COUNTIFS(C6:C105,A123,F6:F105,"Sickness") -> 0 | F123: =COUNTIFS(C6:C105,A123,F6:F105,"PLT") -> 0 | G123: =COUNTIFS(C6:C105,A123,F6:F105,"Study Leave") -> 0 | H123: =COUNTIFS(C6:C105,A123,F6:F105,"Other") -> 0
A124: Bugbrooke Surgery | B124: =COUNTIF(C6:C105,A124) -> 0 | C124: =SUMIF(C6:C105,A124,G6:G105) -> 0 | D124: =COUNTIFS(C6:C105,A124,F6:F105,"Annual Leave") -> 0 | E124: =COUNTIFS(C6:C105,A124,F6:F105,"Sickness") -> 0 | F124: =COUNTIFS(C6:C105,A124,F6:F105,"PLT") -> 0 | G124: =COUNTIFS(C6:C105,A124,F6:F105,"Study Leave") -> 0 | H124: =COUNTIFS(C6:C105,A124,F6:F105,"Other") -> 0
A125: Brook Health Centre | B125: =COUNTIF(C6:C105,A125) -> 0 | C125: =SUMIF(C6:C105,A125,G6:G105) -> 0 | D125: =COUNTIFS(C6:C105,A125,F6:F105,"Annual Leave") -> 0 | E125: =COUNTIFS(C6:C105,A125,F6:F105,"Sickness") -> 0 | F125: =COUNTIFS(C6:C105,A125,F6:F105,"PLT") -> 0 | G125: =COUNTIFS(C6:C105,A125,F6:F105,"Study Leave") -> 0 | H125: =COUNTIFS(C6:C105,A125,F6:F105,"Other") -> 0
A126: Denton Village Surgery | B126: =COUNTIF(C6:C105,A126) -> 0 | C126: =SUMIF(C6:C105,A126,G6:G105) -> 0 | D126: =COUNTIFS(C6:C105,A126,F6:F105,"Annual Leave") -> 0 | E126: =COUNTIFS(C6:C105,A126,F6:F105,"Sickness") -> 0 | F126: =COUNTIFS(C6:C105,A126,F6:F105,"PLT") -> 0 | G126: =COUNTIFS(C6:C105,A126,F6:F105,"Study Leave") -> 0 | H126: =COUNTIFS(C6:C105,A126,F6:F105,"Other") -> 0
A127: TOTAL | B127: =SUM(B120:B126) -> 0 | C127: =SUM(C120:C126) -> 0 | D127: =SUM(D120:D126) -> 0 | E127: =SUM(E120:E126) -> 0 | F127: =SUM(F120:F126) -> 0 | G127: =SUM(G120:G126) -> 0 | H127: =SUM(H120:H126) -> 0
